[{"c":"54778254000164","r":"100SPIN HOTEL FAZENDA GUAPO LTDA","n":"100SPIN HOTEL FAZENDA GUAPO","m":"GUAPO","d":"2024-04-17"},{"c":"63540768000178","r":"63.540.768 RODOLFO ASSIS DE AZEVEDO EM RECUPERACAO JUDICIAL","n":null,"m":"NIQUELANDIA","d":"2025-11-06"},{"c":"66499676000180","r":"A E P MELHORIM AGROPECUARIA","n":"A E P MELHORIM AGROPECUARIA","m":"PETROLINA DE GOIAS","d":"2026-04-28"},{"c":"29406290000230","r":"AGRONEGOCIOALTALUZBRASIL INDUSTRIA E COMERCIO, IMPORTACAO E EXPORTACAO LTDA","n":null,"m":"APARECIDA DE GOIANIA","d":"2020-11-09"},{"c":"29406290000150","r":"AGRONEGOCIOALTALUZBRASIL INDUSTRIA E COMERCIO, IMPORTACAO E EXPORTACAO LTDA","n":"AGRONEGOCIOALTALUZBRASIL","m":"GOIANIA","d":"2018-01-10"},{"c":"01686856000125","r":"AGRONEGOCIOBRASIL INDUSTRIA, COMERCIO, IMPORTACAO E EXPORTACAO S/A","n":"AGRONEGOCIO BRASIL","m":"GOIANIA","d":"1985-11-14"},{"c":"37621729000195","r":"AGROPECUARIA ARANHA LTDA","n":"******************************","m":"URUACU","d":"1992-12-23"},{"c":"38277743000186","r":"AGROPECUARIA GRANDES LAGOS LTDA","n":null,"m":"ARUANA","d":"2020-08-31"},{"c":"96639125000135","r":"ALPHA NEGOCIOS AGROPECUARIOS LTDA","n":null,"m":"ALVORADA DO NORTE","d":"1993-05-05"},{"c":"36444257000180","r":"ALTUM GESTAO LTDA","n":"ALTUM GESTAO","m":"SAO MIGUEL DO PASSA QUATRO","d":"2020-02-20"},{"c":"06979951000130","r":"AMBIENTAL TOLENTINO LTDA","n":"PLANETA AMBIENTAL, EDITAL E CONSTRUCAO","m":"ITAPACI","d":"2004-09-10"},{"c":"58443107000194","r":"ANIBAL VICENTE DA SILVA","n":null,"m":"PALMEIRAS DE GOIAS","d":"2024-12-12"},{"c":"36090528000146","r":"ANTONIO CESAR WESTIN AGUIAR","n":"BARAO RECICLAGEM","m":"QUIRINOPOLIS","d":"2020-01-22"},{"c":"66981880000132","r":"AQUA LAMBARI PISCICULTURA LTDA","n":"AQUA LAMBARI PISCICULTURA","m":"ALEXANIA","d":"2026-05-26"},{"c":"62301670000103","r":"AQUALIS AGROINDUSTRIA E COMERCIO DE PESCADOS LTDA","n":"AQUALIS PESCADOS","m":"LUZIANIA","d":"2025-08-19"},{"c":"01165551000178","r":"ASSOCIACAO AMIGOS DO RIO","n":null,"m":"RIO VERDE","d":"1996-03-19"},{"c":"07654846000194","r":"ASSOCIACAO DE AQUICULTURA E PESCA DE ITUMBIARA-GO","n":"API","m":"ITUMBIARA","d":"2005-05-12"},{"c":"17439254000103","r":"ASSOCIACAO DE AQUICULTURA E PESCA RECANTO DOS AMIGOS","n":"AAPRA","m":"ITUMBIARA","d":"2011-10-07"},{"c":"52836770000172","r":"ASSOCIACAO DE PESCADORES PROFISSIONAIS ARTESANAIS DE INACIOLANDIA","n":"ASSOCIACAO DE PESCADORES PROFISSIONAIS ARTESANAIS","m":"INACIOLANDIA","d":"2023-11-01"},{"c":"19328829000146","r":"ASSOCIACAO DE PESCADORES PROFISSIONAIS E AQUICULTURA DE ITUMBIARA-GO","n":"A.P.P.A.I","m":"ITUMBIARA","d":"2013-11-26"},{"c":"49617233000127","r":"BISTRO CAIPIRA LAS ROSAS LTDA","n":"BISTRO CAIPIRA LAS ROSAS","m":"ALEXANIA","d":"2023-02-15"},{"c":"33942929000199","r":"BUENO E PEIXOTO PISICULTURA POUSADA E PESQUE PAGUE LTDA","n":"BRASIL 21","m":"PADRE BERNARDO","d":"2019-06-17"},{"c":"65610785000160","r":"C A BUENO AGROPECUARIA EM RECUPERACAO JUDICIAL","n":"C A BUENO AGROPECUARIA","m":"JUSSARA","d":"2026-03-10"},{"c":"65635612000104","r":"C A P BUENO AGROPECUARIA EM RECUPERACAO JUDICIAL","n":"C A P BUENO AGROPECUARIA","m":"JUSSARA","d":"2026-03-11"},{"c":"65636662000106","r":"C DE S P BUENO AGROPECUARIA EM RECUPERACAO JUDICIAL","n":"C DE S P BUENO AGROPECUARIA","m":"JUSSARA","d":"2026-03-12"},{"c":"21326453000182","r":"CAMPINA AGROPECUARIA LTDA","n":"AGROPECUARIA INOVA","m":"FLORES DE GOIAS","d":"2014-10-31"},{"c":"41995819000113","r":"CANAL PESCA, CACA E NAUTICA LTDA","n":"CANAL PESCA, CACA E NAUTICA","m":"MORRINHOS","d":"2021-05-18"},{"c":"04702232000142","r":"CENTRO RECREATIVO SEMPRE VERDE LTDA","n":"TRES ILHAS ACQUA PARK","m":"GOIANIA","d":"2001-08-24"},{"c":"66395058000190","r":"CLUBE ESTANCIA DAS FLORES LEILAO, EXPOSICOES E FEIRAS DE AVES LTDA","n":"CLUBE ESTANCIA DAS FLORES LEILAO, EXP. E FEIRA DE AVES","m":"BONFINOPOLIS","d":"2026-04-22"},{"c":"12036701000160","r":"COLONIA DE PESCADORES Z-9 DE NIQUELANDIA","n":"CPN","m":"NIQUELANDIA","d":"2010-06-01"},{"c":"05351874000107","r":"COMERCIAL BATISTA REIS LTDA","n":"COMERCIAL BATISTA REIS","m":"NOVA VENEZA","d":"2002-10-15"},{"c":"17572076000194","r":"COMERCIAL MENDESS LTDA","n":"COMERCIAL MENDESS","m":"NOVA VENEZA","d":"2013-02-14"},{"c":"53912215000145","r":"CONDOMINIO DE PESCARIA E LAZER LAGO BONITO LTDA","n":"CONDOMINIO DE PESCARIA E LAZER LAGO BONITO","m":"URUACU","d":"2024-02-15"},{"c":"59389232000126","r":"CONFIA EMPREENDIMENTOS LTDA","n":"CONFIA DIVERSOES","m":"APARECIDA DE GOIANIA","d":"2025-02-10"},{"c":"39410534000121","r":"DOUGLAS SEITY A FUKUDA LTDA","n":"SEITY COMERCIO E SERVICOS","m":"AURILANDIA","d":"2020-10-14"},{"c":"56340207000160","r":"ESTANCIA ESTRELA DALVA LTDA","n":"ESTANCIA ESTRELA DALVA","m":"ARAGOIANIA","d":"2024-08-07"},{"c":"08698320000179","r":"FILON FERRER - PESQUE E PAGUE LTDA","n":"PESQUE E PAGUE DO NETO","m":"SENADOR CANEDO","d":"2007-03-14"},{"c":"40513135000175","r":"FRIGORIFICO DE PEIXES ABADIANIA LTDA","n":"FRIGORIFICO ESTANCIA RABELO","m":"ABADIANIA","d":"2021-01-22"},{"c":"41644490000146","r":"FRIGORIFICO MASTER PEIXE LTDA","n":"FRIGORIFICO MASTER PEIXE","m":"INACIOLANDIA","d":"2021-04-20"},{"c":"24866287000103","r":"HOTEIS REGGHIS LTDA","n":null,"m":"GOIANIA","d":"1988-03-14"},{"c":"24866287000286","r":"HOTEIS REGGHIS LTDA","n":null,"m":"CRISTALINA","d":"1988-03-15"},{"c":"43204600000184","r":"HOTEL FAZENDA BOA SORTE LTDA","n":"HOTEL FAZENDA BOA SORTE","m":"LUZIANIA","d":"2021-08-20"},{"c":"33445459000158","r":"HOTEL FAZENDA DIAMANTE LTDA","n":"HOTEL FAZENDA DIAMANTE","m":"CATALAO","d":"2019-04-24"},{"c":"66573416000107","r":"J C DE S MELHORIM AGROPECUARIA","n":"J C DE S MELHORIM AGROPECUARIA","m":"PETROLINA DE GOIAS","d":"2026-04-28"},{"c":"59778707000176","r":"J E PINHEIRO CLUBE DE PESCA SABIA 2","n":null,"m":"TRINDADE","d":"2025-03-07"},{"c":"61295202000100","r":"J N PESCADOS LTDA","n":"J N PESCADOS","m":"INACIOLANDIA","d":"2025-06-13"},{"c":"56045920000180","r":"JOEMIR ESIO ALMEIDA DA ROCHA","n":"ESTANCIA DAS AGUAS, PESQUE E PAGUE & RESORT","m":"ESTRELA DO NORTE","d":"2024-07-23"},{"c":"53941156000133","r":"JOQUEI PESCA E LAZER LTDA","n":"JOQUEI PESCA E LAZER","m":"ANAPOLIS","d":"2024-02-16"},{"c":"08973988000187","r":"LUCIJANE VIDAL DE FREITAS LTDA","n":null,"m":"JATAI","d":"2007-08-06"},{"c":"40015135000145","r":"MATEUS SOARES DE OLIVEIRA LTDA","n":"PESQUE CLUBE DO MANE","m":"GOIANIA","d":"2020-12-04"},{"c":"40698931000120","r":"MATUTO SERVICE LTDA","n":"MATUTO PARTICIPACOES","m":"SAO MIGUEL DO ARAGUAIA","d":"2021-02-03"},{"c":"23909226000105","r":"MDR & FACYLLYTY CONTABILIDADE EMPRESARIAL E CONDOMINIAL LTDA","n":"MDR EXCELENCIA CONTABILIDADE EMPRESARIAL E CONDOMINIAL","m":"BELA VISTA DE GOIAS","d":"2016-01-05"},{"c":"49583406000133","r":"MSH PESCADOS LTDA","n":"MSH PESCADOS LTDA","m":"INACIOLANDIA","d":"2023-02-13"},{"c":"49331806000151","r":"O PORTO EMPREENDIMENTOS LTDA","n":"O PORTO","m":"ITUMBIARA","d":"2023-01-25"},{"c":"57629429000160","r":"P H DA SILVA AGROPECUARIA","n":"PAI E FILHO EMPREENDIMENTOS AGRICOLAS","m":"PALMEIRAS DE GOIAS","d":"2024-10-09"},{"c":"54499807000140","r":"PARAISO PESCA & ENTRETENIMENTOS LTDA","n":"PARAISO PESCA & ENTRETENIMENTOS","m":"SANTO ANTONIO DO DESCOBERTO","d":"2024-03-27"},{"c":"59443281000108","r":"PEIXOTO E MARTINS AGRONEGOCIOS LTDA","n":"ACQUA CORUMBA PSICULTURA","m":"ABADIANIA","d":"2025-02-13"},{"c":"49804079000100","r":"PESQUE E PAGUE SAO JOSE LTDA","n":"PESQUE E PAGUE SAO JOSE LTDA","m":"LEOPOLDO DE BULHOES","d":"2023-03-03"},{"c":"65329230000144","r":"PESQUE PAGUE CAIPIRAO LTDA","n":"PESQUE PAGUE CAIPIRAO","m":"TRINDADE","d":"2026-02-25"},{"c":"51496573000199","r":"PESQUE PAGUE FAVO DE MEL LTDA","n":"PESQUE PAGUE FAVO DE MEL","m":"BRAZABRANTES","d":"2023-07-20"},{"c":"45381747000175","r":"PESQUE PAGUE SEMPRE VERDE LTDA","n":"PESQUE PAGUE SEMPRE VERDE","m":"ITUMBIARA","d":"2022-02-21"},{"c":"52785835000106","r":"PESQUE PAGUE TRINDADE LTDA","n":"O PORTO","m":"ITUMBIARA","d":"2023-11-06"},{"c":"10707513000190","r":"POINT DA PESCA CORUMBA LTDA","n":"POINT DA PESCA","m":"SANTO ANTONIO DO DESCOBERTO","d":"2009-03-12"},{"c":"08963918000148","r":"POINT DA PESCA LTDA","n":"POINT DA PESCA CORUMBA LTDA","m":"SANTO ANTONIO DO DESCOBERTO","d":"2007-06-15"},{"c":"55646273000108","r":"PSICULTURA 2T LTDA","n":"PSICULTURA 2T","m":"MONTE ALEGRE DE GOIAS","d":"2024-06-24"},{"c":"05888972000188","r":"QUINTA DO RIANTES RESTAURANTE CHOPARIA E PESCARIA LTDA","n":"QUITA DO RIANTES","m":"JARAGUA","d":"2003-09-02"},{"c":"54416335000114","r":"RANCHO DO MATUTO LTDA","n":"RANCHO DO MATUTO","m":"SAO MIGUEL DO ARAGUAIA","d":"2024-03-21"},{"c":"56961558000198","r":"RECANTO DO SOL PESCA E LAZER LTDA","n":"RECANTO DO SOL PESCA E LAZER","m":"ANAPOLIS","d":"2024-08-22"},{"c":"41223442000346","r":"RR ADMINISTRACAO E NEGOCIOS S/A","n":null,"m":"PIRES DO RIO","d":"2022-04-18"},{"c":"27401543000177","r":"SAMARA SILVA GUIMARAES","n":"SG PESCADOS","m":"INACIOLANDIA","d":"2017-03-28"},{"c":"02827376000108","r":"SANTOS AGROPECUARIA LTDA","n":null,"m":"GOIANIA","d":"1986-10-31"},{"c":"10451871000185","r":"TERRA SOCIAL - CONSULTORIA SOCIAL E AGRONOMICA LTDA","n":"TERRA SOCIAL - CONSULTORIA SOCIAL E AGRONOMICA","m":"GOIANIA","d":"2008-11-05"},{"c":"58025833000197","r":"VALE DO DOURADO PESCA E LAZER LTDA","n":"VALE DO DOURADO PESCA E LAZER","m":"ARAGOIANIA","d":"2024-11-08"},{"c":"37179475000105","r":"VETFARM ASSESSORIA E SERVICOS VETERINARIOS LTDA","n":"VERTFARM AGROPECUARIA","m":"AGUA LIMPA","d":"2020-05-19"}]