[{"c":"50961029000108","r":"AICF ARAGUAIA INDUSTRA E COMERCIO DE FUMO LTDA","n":"FUMOS ARAGUAIA","m":"TRINDADE","d":"2023-06-06"},{"c":"26136810000163","r":"ANDRE M DE AGUIAR","n":"ORGANICA","m":"PIRACANJUBA","d":"2016-09-09"},{"c":"28800857000105","r":"BERRA BODE INDUSTRIA E COMERCIO LTDA","n":"BERRA BODE","m":"ALEXANIA","d":"2017-10-05"},{"c":"09617015000178","r":"CICERO ROSENDO FEITOSA LTDA","n":"RAPE PAI JOAO","m":"GOIANIA","d":"2008-06-11"},{"c":"39538383000191","r":"CRAFT TOBACCO LTDA","n":"CRAFT TOBACCO","m":"PIRACANJUBA","d":"2020-10-23"},{"c":"35151896000194","r":"D. S. DE RESENDE JUNIOR","n":"PALHEIROS BELA VISTA","m":"BELA VISTA DE GOIAS","d":"2019-10-10"},{"c":"34565939000115","r":"FUMOPIL INDUSTRIA E COMERCIO LTDA","n":"RAPE XINGU","m":"ALEXANIA","d":"2019-08-16"},{"c":"55088675000126","r":"IMPERADOR SERTANEJO CIGARRO PALHEIRO LTDA","n":"IMPERADOR SERTANEJO","m":"BONFINOPOLIS","d":"2024-05-10"},{"c":"42686912000109","r":"INDUSTRIA E COMERCIO DE PALHEIROS CABARE LTDA","n":"PALHEIROS CABARE","m":"PIRACANJUBA","d":"2021-07-13"},{"c":"29727927000371","r":"PHHASS COMERCIAL LTDA","n":"PHHASS COMERCIAL","m":"GOIANIA","d":"2018-05-15"},{"c":"53641071000130","r":"VIEIRA E FILHOS INDUSTRIA E COMERCIO LTDA","n":"FUMOS VIEIRA","m":"SANTA HELENA DE GOIAS","d":"2024-01-24"}]