[{"c":"22489981000115","r":"22.489.981 LIVIAN UMBELINA NAVES BORGES","n":null,"m":"GOIANIA","d":"2015-05-20"},{"c":"31872884000106","r":"31.872.884 ELIZABETH PIERETTI","n":null,"m":"SANTA HELENA DE GOIAS","d":"2018-10-26"},{"c":"61510066000116","r":"61.510.066 MOISES LEONIS SOUZA","n":null,"m":"GOIANIA","d":"2025-06-30"},{"c":"24935788000196","r":"AFA INDUSTRIA COMERCIO E SERVICOS LTDA","n":"AFA CAMISETAS E BANDEIRAS","m":"APARECIDA DE GOIANIA","d":"2016-06-03"},{"c":"54898787000180","r":"AK 47 CONFECCOES LTDA","n":"AK 47 CONFECCOES","m":"GOIANESIA","d":"2024-04-26"},{"c":"07708090000119","r":"ASA TECELAGEM LTDA","n":"ASA TECELAGEM","m":"GOIANIA","d":"2005-11-22"},{"c":"11406595000104","r":"AVIAMENTOS EMPORIO LTDA","n":"EMPORIO AVIAMENTOS","m":"GOIANIA","d":"2009-11-13"},{"c":"33867095000102","r":"BR BANDEIRAS E COMUNICACAO VISUAL LTDA","n":"BR BANDEIRAS.","m":"GOIANIA","d":"2019-06-07"},{"c":"42013901000168","r":"BR SOLUCOES INTEGRADAS COMERCIO ATACADISTA E VAREJO LTDA","n":"BR SOLUCOES","m":"APARECIDA DE GOIANIA","d":"2021-05-19"},{"c":"45107194000167","r":"CENTRO AUTOMOTIVO TOP CAR LTDA","n":"TOP CAR PNEUS","m":"AGUAS LINDAS DE GOIAS","d":"2022-02-01"},{"c":"63068846000183","r":"CENTROESTE BANDEIRAS E CAMISETAS LTDA","n":"CENTROESTE BANDEIRAS","m":"APARECIDA DE GOIANIA","d":"2025-10-07"},{"c":"36831980000111","r":"CRIATIVA COMERCIO EM GERAL LTDA","n":"CRIATIVA COMERCIO EM GERAL","m":"LUZIANIA","d":"1991-07-18"},{"c":"35800026000107","r":"DFS COMERCIO DE VESTUARIO LTDA","n":"ATACADAO FELIPE","m":"GOIANIA","d":"2019-12-16"},{"c":"00073031000253","r":"E M DA SILVA, INDUSTRIA COMERCIO E SERVICOS LTDA","n":"SO BANDEIRAS","m":"SAO LUIS DE MONTES BELOS","d":"2024-05-20"},{"c":"00073031000172","r":"E M DA SILVA, INDUSTRIA COMERCIO E SERVICOS LTDA","n":"SO BANDEIRAS","m":"GOIANIA","d":"1982-05-17"},{"c":"35383342000112","r":"EIKA PRODUCOES, EVENTOS E COMERCIO LTDA","n":"EIKA PRODUCOES","m":"GOIANIA","d":"2019-11-01"},{"c":"35053171000163","r":"ELCIO RODRIGUES DOS SANTOS FREITAS 01730138136","n":null,"m":"GOIANIA","d":"2019-10-02"},{"c":"56707608000105","r":"ETH INDUSTRIA E COMERCIO DE CONFECCOES LTDA","n":"ETH","m":"APARECIDA DE GOIANIA","d":"2024-08-14"},{"c":"41848414000152","r":"EVEREST ROUPAS INTIMAS LTDA","n":"EVEREST MEIAS E CUECAS","m":"GOIANIA","d":"2021-05-06"},{"c":"41249929000136","r":"FABRICA DE UNIFORMES JAGUAR LTDA","n":"FABRICA DE UNIFORMES JAGUAR","m":"AGUAS LINDAS DE GOIAS","d":"2021-03-17"},{"c":"40216559000178","r":"GRUPO MMX COMUNICACAO VISUAL LTDA","n":"GRUPO MMX COMUNICACAO VISUAL","m":"GOIANIA","d":"2020-12-29"},{"c":"43019365000170","r":"GT UNIFORMES CONFECCAO LTDA","n":"GT UNIFORMES","m":"ITABERAI","d":"2021-08-06"},{"c":"57693524000122","r":"INDUSTRIA SOUZA PINHEIRO LTDA","n":null,"m":"GOIANIA","d":"2024-10-15"},{"c":"37213023000194","r":"IREAL INDUSTRIA E COMERCIO LTDA","n":"IREAL","m":"GOIANIA","d":"2020-05-22"},{"c":"28319914000139","r":"L E MARTINS INDUSTRIA, COMERCIO E SERVICOS LTDA","n":"SO BANDEIRAS","m":"SENADOR CANEDO","d":"2017-08-02"},{"c":"51857098000139","r":"L&K COMERCIAL LTDA","n":"VILA NATURAL GOIANAPOLIS","m":"GOIANAPOLIS","d":"2023-08-17"},{"c":"37535293000111","r":"LALU BASIC ROUPAS E ACESSORIOS LTDA","n":"SAULLE","m":"GOIANIA","d":"2020-06-25"},{"c":"31895905000109","r":"LICITART REPRESENTACOES E COMERCIO LTDA","n":"RHEGALLO UNIFORMES","m":"MOZARLANDIA","d":"2018-10-30"},{"c":"31895905000362","r":"LICITART REPRESENTACOES E COMERCIO LTDA","n":"RHEGALLO UNIFORMES","m":"RIO VERDE","d":"2025-03-14"},{"c":"31895905000281","r":"LICITART REPRESENTACOES E COMERCIO LTDA","n":null,"m":"BOM JESUS DE GOIAS","d":"2024-08-14"},{"c":"50615423000194","r":"LIDER BANDEIRAS E UNIFORMES LTDA","n":"LIDER BANDEIRAS E UNIFORMES","m":"APARECIDA DE GOIANIA","d":"2023-05-10"},{"c":"44837533000106","r":"LOURDES APARECIDA DE PAULA LIMA 01709843110","n":null,"m":"BURITI DE GOIAS","d":"2022-01-12"},{"c":"49361772000148","r":"LRB INDUSTRIA E COMERCIO DE CONFECCOES LTDA","n":"MASTERDOM","m":"APARECIDA DE GOIANIA","d":"2023-01-27"},{"c":"55167921000135","r":"LUCK COMERCIO DE MODA INTIMA LTDA","n":"LUCK MODA INTIMA","m":"GOIANIA","d":"2024-05-17"},{"c":"54767147000130","r":"M&A ROUPAS INDUSTRIAIS LTDA","n":"M&A ROUPAS INDUSTRIAIS","m":"NOVO GAMA","d":"2024-04-17"},{"c":"38407451000110","r":"M4 INDUSTRIA COMERCIO E SERVICOS LTDA","n":"M4 INDUSTRIA COMERCIO E SERVICOS","m":"GOIANIA","d":"2020-09-10"},{"c":"18627195000593","r":"MASTER INDUSTRIA E COMERCIO LTDA","n":"MASTER INDUSTRIA E COMERCIO LTDA","m":"GOIANIA","d":"2021-05-11"},{"c":"27979512000106","r":"MAXIMUS UNIFORMES LTDA","n":"MAXIMUS UNIFORMES","m":"VALPARAISO DE GOIAS","d":"2017-06-16"},{"c":"08007677000163","r":"MPL INDUSTRIA E COMERCIO DE ROUPAS LTDA","n":"M. POLLO E PACO","m":"APARECIDA DE GOIANIA","d":"2006-05-19"},{"c":"34984846000125","r":"MUNDIAL BANDEIRAS INDUSTRIA E COMERCIO LTDA","n":"MUNDIAL BANDEIRAS","m":"TRINDADE","d":"2019-09-25"},{"c":"14502246000176","r":"NOE CORREIA DA PAZ","n":"ENXOVAIS HEMORY","m":"GOIANESIA","d":"2011-10-23"},{"c":"11737128000159","r":"OLF MODAS E VESTUARIO LTDA","n":"OLF","m":"GOIANIA","d":"2010-03-24"},{"c":"41720999000120","r":"PEQUENO KLEIN LTDA","n":"PEQUENO KLEIN KIDS","m":"ANAPOLIS","d":"2021-04-27"},{"c":"46851057000103","r":"PRADO E MORAES LTDA","n":"DEFINITIVA MODA INTIMA","m":"GOIANIA","d":"2022-06-21"},{"c":"05283628000165","r":"R. D. CONFECCOES LTDA","n":"DI RAMOS","m":"GOIANIA","d":"2002-09-16"},{"c":"58541919000172","r":"RODRIGUES E VIEIRA CONFECCOES LTDA","n":"ALFA SERVICE","m":"GOIANIA","d":"2024-12-23"},{"c":"41832434000135","r":"S. A. VITORIA LTDA","n":"SA VITORIA","m":"GOIANESIA","d":"2021-05-05"},{"c":"59664277000161","r":"SOCIAL MODA INTIMA LTDA","n":"SOCIAL MODA INTIMA","m":"GOIANIA","d":"2025-02-26"},{"c":"09109192000143","r":"THP COMERCIO E INDUSTRIA LTDA","n":null,"m":"ITUMBIARA","d":"2007-09-03"},{"c":"46865779000109","r":"VISA MODA INTIMA LTDA","n":"VISA MODA INTIMA","m":"GOIANIA","d":"2022-06-22"},{"c":"39973298000151","r":"WGS COMERCIO E SERVICOS LTDA","n":"ESTACAO DO PAO E SERVICOS","m":"PALMEIRAS DE GOIAS","d":"2020-12-01"}]