[{"c":"21308039000140","r":"21.308.039 EDINA MARIA NEVES GUEDES","n":null,"m":"CAMPESTRE DE GOIAS","d":"2014-10-29"},{"c":"22043358000134","r":"22.043.358 ARNALDO MENDES COELHO JUNIOR","n":null,"m":"GOIANIRA","d":"2015-03-13"},{"c":"22821302000163","r":"22.821.302 ELIDA FERNANDES BARREIROS","n":null,"m":"VALPARAISO DE GOIAS","d":"2015-07-09"},{"c":"22883795000166","r":"22.883.795 ELIENE NASCIMENTO DE SOUSA","n":null,"m":"CRISTALINA","d":"2015-07-20"},{"c":"23627548000161","r":"23.627.548 FABRICIO FERNANDES BRITO","n":null,"m":"GOIANIA","d":"2015-11-09"},{"c":"24050274000153","r":"24.050.274 MARIA MADALENA DIAS DE ALMEIDA","n":null,"m":"CAMPINORTE","d":"2016-01-26"},{"c":"33513495000101","r":"33.513.495 CHARLLES RAMOS SILVERIO","n":null,"m":"GOIANIA","d":"2019-05-02"},{"c":"37129078000110","r":"37.129.078 EMERSON FARIA BEIRIGO","n":null,"m":"GOIANIA","d":"2020-05-13"},{"c":"37844278000155","r":"37.844.278 JULIANA CARVALHO DOS SANTOS","n":null,"m":"AGUAS LINDAS DE GOIAS","d":"2020-07-24"},{"c":"38171287000195","r":"38.171.287 EDUARDO FILIPE QUEIROZ PIMENTEL CINTRA","n":null,"m":"GOIANIA","d":"2020-08-20"},{"c":"39437320000149","r":"39.437.320 CRISTIANE ALVES AGUIAR RODRIGUES","n":null,"m":"VALPARAISO DE GOIAS","d":"2020-10-15"},{"c":"40682417000104","r":"40.682.417 ESTEFANIA CAROLINE DE ARAUJO NOBREGA","n":null,"m":"MINEIROS","d":"2021-02-02"},{"c":"41538172000109","r":"41.538.172 LINDOMAR CICERO DE OLIVEIRA","n":null,"m":"ANAPOLIS","d":"2021-04-12"},{"c":"42063092000107","r":"42.063.092 BRUNA RIBEIRO ROCHA SILVA","n":null,"m":"ANAPOLIS","d":"2021-05-24"},{"c":"43797397000105","r":"43.797.397 ROBERTA ANCELMO DE OLIVEIRA","n":null,"m":"RIO VERDE","d":"2021-10-06"},{"c":"44592833000164","r":"44.592.833 DENISE DE SOUZA","n":null,"m":"GOIANIA","d":"2021-12-15"},{"c":"44604541000102","r":"44.604.541 MATHEUS VASCONCELOS DOS SANTOS","n":null,"m":"ALTO PARAISO DE GOIAS","d":"2021-12-15"},{"c":"44814462000118","r":"44.814.462 PATRICIA BARBARA DE CASTILHO","n":null,"m":"ITAPACI","d":"2022-01-11"},{"c":"45221432000160","r":"45.221.432 JAQUELINE GONCALVES MORAES","n":null,"m":"AGUAS LINDAS DE GOIAS","d":"2022-02-09"},{"c":"45613061000162","r":"45.613.061 CRISTIANO TEIXEIRA DOS SANTOS","n":null,"m":"SANTA HELENA DE GOIAS","d":"2022-03-11"},{"c":"47471766000118","r":"47.471.766 DELCIO ALVES SCHIOCHET","n":null,"m":"FORMOSA","d":"2022-08-08"},{"c":"48771457000126","r":"48.771.457 MONIKE ESTEFHANI FERNANDES GALVAO","n":null,"m":"APARECIDA DE GOIANIA","d":"2022-11-30"},{"c":"49077906000101","r":"49.077.906 ELITAMAR ROCHA DE SOUZA","n":null,"m":"ANAPOLIS","d":"2023-01-05"},{"c":"49122976000126","r":"49.122.976 JEDER GUEDES LIMA ROCHA","n":null,"m":"FORMOSA","d":"2023-01-10"},{"c":"49559395000156","r":"49.559.395 LUIS FELLIPE RODRIGUES SILVA","n":null,"m":"ITAUCU","d":"2023-02-10"},{"c":"51890430000167","r":"51.890.430 CARLOS HELI DA SILVA NOGUEIRA","n":null,"m":"GOIANIA","d":"2023-08-21"},{"c":"52104195000113","r":"52.104.195 MARIA EDUARDA MARTINS MADY","n":"HASHTAG PRINT GRAFICA","m":"GOIANIA","d":"2023-09-06"},{"c":"56251557000150","r":"56.251.557 DEBORAH LIMA FERNANDES","n":null,"m":"GOIANIA","d":"2024-08-03"},{"c":"57178911000120","r":"57.178.911 JOSE MARCOS DOS SANTOS","n":null,"m":"APARECIDA DE GOIANIA","d":"2024-09-06"},{"c":"63947858000188","r":"63.947.858 MARIO JUNIOR HOICA","n":null,"m":"CHAPADAO DO CEU","d":"2025-12-05"},{"c":"07579663000151","r":"A EFICAZ COMERCIO E PRESTACAO DE SERVICOS GRAFICOS LTDA","n":"EFICAZ","m":"GOIANIA","d":"2005-08-17"},{"c":"08787226000196","r":"ABPLASTIC - INDUSTRIA DE EMBALAGENS LTDA","n":"AB - PLASTIC","m":"GOIANIA","d":"2007-04-20"},{"c":"24935788000196","r":"AFA INDUSTRIA COMERCIO E SERVICOS LTDA","n":"AFA CAMISETAS E BANDEIRAS","m":"APARECIDA DE GOIANIA","d":"2016-06-03"},{"c":"55016840000134","r":"AIDERBOX LTDA","n":"AIDERBOX","m":"GOIANIA","d":"2024-05-06"},{"c":"21997920000104","r":"ALBA SACOLAS PERSONALIZADAS LTDA","n":"ALBA SACOLAS","m":"GOIANIA","d":"2015-03-06"},{"c":"24023204000106","r":"ALL PRINT EXPRESS IMPRESSOES E EMBALAGENS LTDA","n":"ALL PRINT EXPRESS IMPRESSOES E EMBALAGENS","m":"APARECIDA DE GOIANIA","d":"2016-01-21"},{"c":"82637109001928","r":"ALL4LABELS GRAFICA DO BRASIL LTDA","n":null,"m":"ANAPOLIS","d":"2025-08-26"},{"c":"82637109002061","r":"ALL4LABELS GRAFICA DO BRASIL LTDA","n":null,"m":"ANAPOLIS","d":"2025-08-26"},{"c":"29708563000110","r":"ALUT PLASTICO LTDA","n":null,"m":"TRINDADE","d":"2018-02-19"},{"c":"50739571000110","r":"AMAZON SISTEMAS INTERGRAFICOS LTDA","n":"GRAFISA","m":"ANAPOLIS","d":"2023-05-19"},{"c":"53448307000116","r":"AME EXP DIGITAL LTDA","n":"AME EXP DIGITAL","m":"GOIANAPOLIS","d":"2024-01-10"},{"c":"53603158000112","r":"AMERICAN EX S A LTDA","n":"AMERICAN EX S A","m":"GOIANIA","d":"2024-01-22"},{"c":"47044427000155","r":"AP EMBALAGENS LTDA","n":"AP EMBALAGENS","m":"GOIANIA","d":"2022-07-06"},{"c":"33226010000107","r":"ARPEL ARTEFATOS DE PAPEL LTDA","n":"ARPEL","m":"GOIANIA","d":"1989-06-02"},{"c":"59515307000178","r":"ARTE CRIATIVA GYN LTDA","n":"ARTE CRIATIVA GYN","m":"GOIANIA","d":"2025-02-17"},{"c":"57627052000100","r":"ARTEVISUAL LTDA","n":"ARTEVISUAL","m":"OUVIDOR","d":"2024-10-09"},{"c":"45960882000175","r":"ASPEL INDUSTRIA E COMERCIO DE EMBALAGENS LTDA","n":"ASPEL EMBALAGENS","m":"APARECIDA DE GOIANIA","d":"2022-04-08"},{"c":"45575306000104","r":"ATELIE DAS FORMINHAS LTDA","n":"DOCE FLOR FORMINHAS","m":"SENADOR CANEDO","d":"2022-03-09"},{"c":"66837751000175","r":"ATLA COPOS LTDA","n":null,"m":"GOIANIA","d":"2026-05-18"},{"c":"41350845000194","r":"ATRES GRAFICA LTDA","n":"ATRES GRAFICA","m":"GOIANIA","d":"2021-03-25"},{"c":"17041177000139","r":"ATTO INDUSTRIA E COMERCIO DE EMBALAGENS LTDA","n":"ATTO EMBALAGENS","m":"GOIANIA","d":"2012-10-22"},{"c":"48997048000142","r":"AURORA INDUSTRIA DE TINTAS E SOLVENTES LTDA","n":"AURORA INDUSTRIA DE TINTAS E SOLVENTES","m":"RIO VERDE","d":"2022-12-28"},{"c":"11406595000104","r":"AVIAMENTOS EMPORIO LTDA","n":"EMPORIO AVIAMENTOS","m":"GOIANIA","d":"2009-11-13"},{"c":"47602835000185","r":"AZUK IMPRESSAO E COMUNICACAO LTDA","n":"AZUK IMPRESSAO E COMINUCACAO","m":"GOIANIA","d":"2022-08-17"},{"c":"08749041000197","r":"BALTHAZAR E BALTHAZAR COMERCIO ATACADISTA DE EMBALAGENS LTDA","n":"NATURAL EMBALAGENS","m":"APARECIDA DE GOIANIA","d":"2007-04-04"},{"c":"21369255000104","r":"BIANCA KRISTINA PIRES MENDANHA ADORNO 02578267189","n":null,"m":"GOIANIA","d":"2014-11-10"},{"c":"36260095000120","r":"BIO PAPER INDUSTRIA E COMERCIO DE EMBALAGENS LTDA","n":"BIO PAPER EMBALAGENS","m":"ANAPOLIS","d":"2020-02-05"},{"c":"50156085000170","r":"BOAZ TRANSPORTE LOGISTICA LTDA","n":"BOAZ TRANSPORTES","m":"GOIANIA","d":"2023-03-31"},{"c":"03009846000180","r":"BOKOBRAS EMBALAGENS INDUSTRIA E COMERCIO LTDA","n":"BOKOS EMBALAGENS","m":"LUZIANIA","d":"1999-01-06"},{"c":"51813460000170","r":"BR PACKS EMBALAGENS LTDA","n":"BR PACKS EMBALAGENS","m":"APARECIDA DE GOIANIA","d":"2023-08-15"},{"c":"40669383000100","r":"BRAND DE COMUNICACAO: MARKETING, PUBLICIDADE, SERVICOS GRAFICOS E JN O NORTE DE GOIAS LTDA","n":"GRUPO BRAND DE COMUNICACAO","m":"MINACU","d":"2021-02-02"},{"c":"04574911000183","r":"C & A EMBALAGENS LTDA","n":"CARTOBISA EMBALAGENS","m":"ANAPOLIS","d":"2001-07-18"},{"c":"12159852000105","r":"C & D INDUSTRIA E COMERCIO LTDA","n":"C & D CARTONAGEM","m":"RIO VERDE","d":"2010-07-05"},{"c":"36330701000136","r":"C3 ARTES & GRAFICA LTDA","n":"GURUARTES GRAFICA","m":"MOZARLANDIA","d":"2020-02-11"},{"c":"35573691000105","r":"CAIXAS PAPELAO GOIANIA COMERCIO ATACADISTA DE EMBALAGENS LTDA","n":"CAIXAS PAPELAO GOIANIA","m":"APARECIDA DE GOIANIA","d":"2019-11-21"},{"c":"32415110000100","r":"CARMEM LORENA BARBOSA LOPES 02016536136","n":"LOJA DE BALOES E DECORACOES LORENA LOPES","m":"ITUMBIARA","d":"2019-01-10"},{"c":"25121120000178","r":"CARTONAGEM E LITOGRAFIA ANAPOLINA LTDA","n":null,"m":"ANAPOLIS","d":"1989-04-18"},{"c":"56106121000177","r":"CARTONAGEM INFINITY LTDA","n":"INFINITY GRAFICA","m":"GOIANIA","d":"2024-07-26"},{"c":"34307302000129","r":"CARTONAGEM PAIVA INDUSTRIA E COMERCIO LTDA","n":"CARTONAGEM PAIVA EMBALAGENS","m":"GOIANIA","d":"2019-07-24"},{"c":"09292383000193","r":"CARTONGRAPH INDUSTRIA GRAFICA E EMBALAGENS LTDA.","n":"CARTONGRAPH","m":"ANAPOLIS","d":"2008-01-08"},{"c":"61573916000125","r":"CARVALHO PACK E ALIMENTOS LTDA","n":"QUINTA DO CARVALHO","m":"TEREZOPOLIS DE GOIAS","d":"2025-07-03"},{"c":"49385823000171","r":"CENTRAL PALETES E PAPEIS LTDA","n":"CENTRAL PALETES E PAPEIS","m":"FORMOSA","d":"2023-01-30"},{"c":"03220972000180","r":"CENTRO OESTE INDUSTRIA COMERCIO LOGISTICA E TRANSPORTE LTDA","n":"CENTRO OESTE INDUSTRIA","m":"ANAPOLIS","d":"1999-06-15"},{"c":"49825762000116","r":"CENTROPACK EMBALAGENS LTDA","n":null,"m":"GOIANIA","d":"2023-03-06"},{"c":"53744294000122","r":"CENTROPACK GYN EMBALAGENS LTDA","n":"CENTROPACK EMBALAGENS","m":"GOIANIA","d":"2024-01-31"},{"c":"57069169000115","r":"CK PRINTT GRAFICA RAPIDA LTDA","n":"CK PRINTT GRAFICA","m":"TRINDADE","d":"2024-08-29"},{"c":"37887364000145","r":"CLICHETECH LTDA","n":null,"m":"GOIANIA","d":"2020-07-28"},{"c":"37048816000103","r":"COLOR FLEXO INDUSTRIA E COMERCIO DE ETIQUETAS LTDA","n":"COLOR FLEXO ETIQUETAS E ROTULOS","m":"GOIANIA","d":"1992-04-28"},{"c":"07827011000199","r":"COLORFLEXO ETIQUETAS LTDA","n":"COLORFLEXO ETIQUETAS","m":"GOIANIA","d":"2006-01-30"},{"c":"43727347000143","r":"COMERCIAL DE EMBALAGENS LAZIZ KAMAL GOLDENPACK LTDA","n":"GOLDENPACK EMBALAGENS","m":"CIDADE OCIDENTAL","d":"2021-10-01"},{"c":"03852660000199","r":"CP KRAFT EMBALAGENS LTDA","n":"CP KRAFT","m":"GOIANIA","d":"2000-05-31"},{"c":"44258562000105","r":"CRASLEI E SERAVALI IND DE EMBALAGENS LTDA","n":"EMBALAGENS E CARTONAGEM LITTLE ITALY","m":"INHUMAS","d":"2021-11-16"},{"c":"38446931000190","r":"CRIAR COMUNICACAO VISUAL LTDA","n":null,"m":"GOIATUBA","d":"2020-09-14"},{"c":"52905651000124","r":"CRIATIVABR EMBALAGENS LTDA","n":"CRIATIVABR EMBALAGENS","m":"CALDAS NOVAS","d":"2023-11-16"},{"c":"15799027000163","r":"D O SILVA SERVICOS E EMPREENDIMENTOS LTDA","n":null,"m":"JARAGUA","d":"2012-06-21"},{"c":"51336971000148","r":"DD SERVICOS LTDA","n":null,"m":"GOIANIA","d":"2023-07-07"},{"c":"14855648000154","r":"DECORA FESTAS LTDA","n":"DECORA DOCES","m":"GOIANIA","d":"2012-01-10"},{"c":"51329617000196","r":"DF SERVICOS ADMINISTRATIVOS LTDA","n":null,"m":"GOIANIA","d":"2023-07-06"},{"c":"17105850000157","r":"DIAS E ROCHA LTDA","n":"OFF SET ADESIVOS","m":"GOIANIA","d":"2012-11-01"},{"c":"54952261000130","r":"DINAMIC MARCENARIA E COMUNICACAO VISUAL LTDA","n":"DM MONTAGENS","m":"GOIANIA","d":"2024-04-30"},{"c":"20922004000134","r":"DIONISIO DE LUCIA NETTO LTDA","n":"M3 PAPEIS","m":"GOIANIA","d":"2014-08-27"},{"c":"47114915000191","r":"DM EXPRESS PRESTACAO DE SERVICOS LTDA","n":"EXPRESS SERVICOS","m":"GOIANIA","d":"2022-07-12"},{"c":"22813138000142","r":"DOCE E FESTA LTDA","n":"DOCE E FESTA","m":"CACU","d":"2015-07-08"},{"c":"63277724000105","r":"DRUCKHAUS INDUSTRIA DE EMBALAGENS LTDA","n":"DRUCKHAUS EMBALAGENS","m":"ANAPOLIS","d":"2025-10-20"},{"c":"28649165000108","r":"E.M. INDUSTRIA E COMERCIO DE EMBALAGENS PLASTICAS LTDA","n":"BAJA INDUSTRIA E COMERCIO DE EMBALAGENS PLASTICAS","m":"ARAGUAPAZ","d":"2017-09-15"},{"c":"02854218000139","r":"EBENEZER RODRIGUES LTDA","n":"EMBALAGENS EBENEZER","m":"ALEXANIA","d":"1998-11-19"},{"c":"11928775000148","r":"ECOPEL INDUSTRIA E COMERCIO LTDA","n":"ECOPEL INDUSTRIA","m":"SANTA RITA DO ARAGUAIA","d":"2010-05-12"},{"c":"27232888000144","r":"EDNAIANE GOMES FERREIRA 87677113249","n":null,"m":"GOIANIA","d":"2017-03-06"},{"c":"24823145000150","r":"EGM SERVICOS GRAFICOS LTDA","n":"EGM GRAFICA","m":"AGUAS LINDAS DE GOIAS","d":"2016-05-18"},{"c":"35383342000112","r":"EIKA PRODUCOES, EVENTOS E COMERCIO LTDA","n":"EIKA PRODUCOES","m":"GOIANIA","d":"2019-11-01"},{"c":"07570962000125","r":"EMBALAGENS ALLBOX LTDA","n":"ALLBOX INDUSTRIA GRAFICA","m":"ANAPOLIS","d":"2005-08-17"},{"c":"04452368000141","r":"EMBALAGENS MOARA LTDA","n":"MOARA EMBALAGENS","m":"ANAPOLIS","d":"2001-05-17"},{"c":"42605067000108","r":"EMBALAGENS VITORIA LTDA","n":"EMBALAGENS VITORIA","m":"GOIANIA","d":"2021-07-06"},{"c":"57990296000152","r":"EMBALLA DOCES LTDA","n":"DECORA DOCES","m":"GOIANIA","d":"2024-11-06"},{"c":"67202206000175","r":"ENCANTTA COMERCIO DE FORMAS E EMBALAGENS LTDA","n":"ENCANTTA FORMINHAS E EMBALAGENS","m":"GOIANIA","d":"2026-05-29"},{"c":"42276885000104","r":"ESPETOGIN ALIMENTOS LTDA","n":"ESPETOGIN ALIMENTOS","m":"GOIANIA","d":"2021-06-10"},{"c":"50381972000141","r":"ESTUDIO D FORMATURA BECAS E CANUDOS LTDA","n":null,"m":"GOIANIA","d":"2023-04-19"},{"c":"37305471000118","r":"EVOLUM INDUSTRIA E COMERCIO DE EMBALAGENS LTDA","n":"EVOLUM EMBALAGENS FLEXIVEIS","m":"APARECIDA DE GOIANIA","d":"1992-03-23"},{"c":"60772810000198","r":"EXCELENCIA COMUNICACAO INTEGRADA - SLU LTDA","n":"ILUSTRE GRAFICA E COMUNICACAO VISUAL","m":"ABADIA DE GOIAS","d":"2025-05-12"},{"c":"22197613000101","r":"EXPRESS ETIQUETAS LTDA","n":"EXPRESS ETIQUETAS","m":"GOIANIA","d":"2015-04-06"},{"c":"20489725000100","r":"FA INDUSTRIA E COMERCIO DE ALIMENTOS LTDA","n":"F A ALIMENTOS","m":"GOIANIA","d":"2014-06-24"},{"c":"10467383000166","r":"FACA FESTA INDUSTRIA, COMERCIO E DISTRIBUICAO DE ARTIGOS PARA FESTAS LTDA","n":"FACA FESTA","m":"ANAPOLIS","d":"2008-11-10"},{"c":"01303730000124","r":"FARPEL FABRICA DE ARTEFATOS DE PAPEIS LTDA","n":null,"m":"GOIANIA","d":"1996-07-10"},{"c":"38454496000146","r":"FAST PRINT JARAGUA SERVICOS E EMPREENDIMENTOS LTDA","n":"FAST PRINT JARAGUA","m":"JARAGUA","d":"2020-09-14"},{"c":"33448949000108","r":"FERC GRAFICA E EMBALAGENS LTDA","n":"FERC GRAFICA E EMBALAGENS","m":"GOIANIA","d":"2019-04-24"},{"c":"48412512000191","r":"FGX GRAFICA REPRESENTACOES E EVENTOS LTDA","n":"NEXUS","m":"GOIANIA","d":"2022-10-26"},{"c":"28688292000116","r":"FLASHPRINT GRAFICA E EDITORA LTDA","n":"FLASHPRINT","m":"APARECIDA DE GOIANIA","d":"2017-09-20"},{"c":"37832508000166","r":"FLORAX E GLOBO COMERCIO DE PAPEIS LTDA","n":"GUARDANAPOS FLORAX","m":"ANAPOLIS","d":"1993-05-10"},{"c":"37832508000247","r":"FLORAX E GLOBO COMERCIO DE PAPEIS LTDA","n":"CARTONAGEM FLORAX","m":"LUZIANIA","d":"2024-09-26"},{"c":"66742217000185","r":"FNG SOLUCOES GRAFICA LTDA","n":"FNG SOLUCOES GRAFICA","m":"NEROPOLIS","d":"2026-05-08"},{"c":"46137609000108","r":"FORTS SACOLAS PERSONALIZADAS LTDA","n":"FORTS SACOLAS PERSONALIZADAS","m":"ANAPOLIS","d":"2022-04-25"},{"c":"34439724000158","r":"FRANCISCO LUIZ RODRIGUES TORRES 27791793172","n":null,"m":"RIO VERDE","d":"2019-08-06"},{"c":"60906840000140","r":"G DE OLIVEIRA MASTERPLASTIC LTDA","n":"MASTERPLASTIC","m":"GOIANIA","d":"2025-05-20"},{"c":"64433090000197","r":"GAB INDUSTRIA GRAFICA LTDA","n":"NATUCOPOS EXPRESS","m":"NEROPOLIS","d":"2026-01-07"},{"c":"66637192000150","r":"GDF CARTUCHOS LTDA","n":"GDF CARTUCHOS","m":"ANAPOLIS","d":"2026-05-06"},{"c":"17934853000101","r":"GERMAM GRAFICA LTDA","n":"GERMAM ACABAMENTOS","m":"GOIANIA","d":"2013-04-15"},{"c":"31128477000180","r":"GILBENIO COSTA DOS SANTOS 79450270163","n":null,"m":"ANAPOLIS","d":"2018-08-06"},{"c":"48290999000187","r":"GL MONTAGENS E SERVICOS MULTIPLOS DINAMIC LTDA","n":"DINAMIC","m":"GOIANIA","d":"2022-10-14"},{"c":"30199070000181","r":"GOIAS INDUSTRIA E COMERCIO DE BOBINAS LTDA","n":"BOBINAS GOIAS","m":"ABADIA DE GOIAS","d":"2018-04-13"},{"c":"33547411000150","r":"GOIASPLASTIC IND E COM DE PLASTICOS LTDA","n":"GOIASPLASTIC","m":"GOIANIA","d":"2019-05-07"},{"c":"24917762000115","r":"GOLDENPEL INDUSTRIA DE ARTEFATOS COMERCIO DE PAPEIS E SERVICOS ESPECIAIS LTDA","n":"GOLDENPEL","m":"GOIANIA","d":"2016-06-01"},{"c":"18840274000154","r":"GRAFICA A.B. LTDA","n":"GRAFICA EMBALA MAIS","m":"GOIANIA","d":"2013-09-09"},{"c":"37029925000175","r":"GRAFICA ALZIRAO DETALS LTDA","n":"ALZIRAO GRAFICA EMPRESA","m":"GOIANIA","d":"2020-04-29"},{"c":"02633048000162","r":"GRAFICA AMAZONAS E EDITORA LTDA","n":null,"m":"APARECIDA DE GOIANIA","d":"1979-04-09"},{"c":"60691511000129","r":"GRAFICA APARECIDA SERVICOS LTDA","n":"GRAFICA APARECIDA SERVICOS","m":"APARECIDA DE GOIANIA","d":"2025-05-06"},{"c":"02911413000234","r":"GRAFICA DA FAMILIA LTDA","n":"GDF BULAS E ROTULOS ADESIVOS","m":"NEROPOLIS","d":"2025-04-25"},{"c":"02911413000153","r":"GRAFICA DA FAMILIA LTDA","n":"NATUCOPOS","m":"NEROPOLIS","d":"1998-12-17"},{"c":"43776933000188","r":"GRAFICA DO VALE IMPRESSAO DIGITAL E EMPREENDIMENTOS LTDA","n":"GRAFICA DO VALE","m":"JARAGUA","d":"2021-10-05"},{"c":"04134374000150","r":"GRAFICA E EDITORA FABERPRINT LIMITADA","n":"FABERPRINT INDUSTRIA GRAFICA","m":"ANAPOLIS","d":"2000-11-01"},{"c":"33547704000138","r":"GRAFICA E EDITORA FORMATO LTDA","n":"GRAFICA FORMATO","m":"APARECIDA DE GOIANIA","d":"1989-12-28"},{"c":"10575202000115","r":"GRAFICA E EDITORA MRL LTDA","n":"MR.","m":"APARECIDA DE GOIANIA","d":"2009-01-15"},{"c":"42659013000117","r":"GRAFICA EDITORA PREMIUM E COMERCIO LTDA","n":"GRAFICA EDITORA PREMIUM E COMERCIO","m":"APARECIDA DE GOIANIA","d":"2021-07-09"},{"c":"06302743000100","r":"GRAFICA MOURA LTDA","n":"GRAFICA MOURA","m":"APARECIDA DE GOIANIA","d":"2004-06-01"},{"c":"04942046000180","r":"GRAFICA NAZPER LTDA","n":"GRAFICA NAZPER","m":"LUZIANIA","d":"2002-03-06"},{"c":"22678655000156","r":"GRAFICA PIRES DO RIO LTDA","n":"ARRIETA PRINT","m":"PIRES DO RIO","d":"2015-06-17"},{"c":"30549391000169","r":"GRAFICA VIDEIRA LTDA","n":"GRAFICA VIDEIRA","m":"GOIANIA","d":"2018-05-24"},{"c":"02702496000170","r":"GRAFIGEL EMBALAGENS LTDA EM RECUPERACAO JUDICIAL","n":"IGEL EMBALAGENS","m":"GOIANIA","d":"1979-07-10"},{"c":"31973684000131","r":"HEAVY PAPER EMBALAGENS LTDA","n":"HEAVY PAPER EMBALAGENS","m":"SENADOR CANEDO","d":"2018-11-08"},{"c":"01832372000147","r":"HEBRON GRAFICA E MARKETING LTDA","n":"HEBRON GRAFICA","m":"GOIANIA","d":"1997-05-07"},{"c":"61734882000103","r":"HERMON PACKING LTDA","n":"HERMON PACKING","m":"ANAPOLIS","d":"2025-07-14"},{"c":"57345406000123","r":"HF MULTISERVICE LTDA","n":null,"m":"APARECIDA DE GOIANIA","d":"2024-09-18"},{"c":"19578170000186","r":"I2IMPRESSOS ETIQUETAS E ROTULOS LTDA","n":"I2IMPRESSOS","m":"GOIANIA","d":"2014-01-23"},{"c":"38545504000160","r":"IBOX INDUSTRIA DE EMBALAGEM LTDA","n":"IBOX INDUSTRIA DE EMBALAGEM","m":"APARECIDA DE GOIANIA","d":"2020-09-18"},{"c":"13547230000117","r":"IMPRESS COMUNICACAO LTDA","n":"IMPRESS","m":"INHUMAS","d":"2011-04-18"},{"c":"40549849000133","r":"INACIA D ABADIA DE SOUZA 60678518149","n":null,"m":"ANAPOLIS","d":"2021-01-25"},{"c":"22562026000166","r":"INBOX INDUSTRIA E COMERCIO DE EMBALAGENS LTDA.","n":"INBOX EMBALAGENS","m":"GOIANIA","d":"2015-05-29"},{"c":"33537697000193","r":"IND. COM. DE GUARDANAPOS E FERRAGENS AURORA LTDA","n":"FERRAGENS AURORA CENTER","m":"ANAPOLIS","d":"1990-01-05"},{"c":"01605716000185","r":"INDUSTRIA GOIANA DE EMBALAGENS LTDA EM RECUPERACAO JUDICIAL","n":"IGEL","m":"GOIANIA","d":"1973-04-06"},{"c":"18691224000152","r":"INFINITY GRAFICA E EDITORA LTDA","n":"INFINITY GRAFICA","m":"GOIANIA","d":"2013-07-25"},{"c":"45100587000149","r":"INNOVA ETIQUETAS LTDA","n":"INNOVA ETIQUETAS","m":"GOIANIA","d":"2022-02-01"},{"c":"20546645000131","r":"INNOVA GRAFICA E EDITORA LTDA","n":"GRAFICA FOCO","m":"GOIANIA","d":"2014-07-02"},{"c":"37228355000142","r":"INOVAR FESTAS LTDA","n":"INOVAR","m":"MAMBAI","d":"2020-05-26"},{"c":"03847530000168","r":"IPANEMA GRAFICA E EDITORA LTDA","n":"GRAFICA IPANEMA","m":"APARECIDA DE GOIANIA","d":"1987-10-29"},{"c":"37213023000194","r":"IREAL INDUSTRIA E COMERCIO LTDA","n":"IREAL","m":"GOIANIA","d":"2020-05-22"},{"c":"37843596000100","r":"ISRAEL COMERCIAL DE EMBALAGENS LTDA","n":"ISRAEL EMBALAGENS","m":"APARECIDA DE GOIANIA","d":"1993-06-16"},{"c":"08990849000161","r":"JAEPEL INDUSTRIA DE PAPEIS LTDA","n":null,"m":"SENADOR CANEDO","d":"2007-07-17"},{"c":"06142539000161","r":"JAEPEL PAPEIS E EMBALAGENS S.A","n":null,"m":"SENADOR CANEDO","d":"2004-03-05"},{"c":"03460742000198","r":"JB GRAFICA E COMUNICACAO VISUAL LTDA","n":"XPRINT GRAFICA","m":"GOIANIA","d":"1999-08-06"},{"c":"40576364000139","r":"JFN BRASIL COMERCIO E SERVICOS LTDA","n":"JFN BRASIL","m":"ANAPOLIS","d":"2021-01-26"},{"c":"19380966000120","r":"JULIANO ALVES MOREIRA","n":"J. MOREIRA - PAPEIS","m":"GOIANIA","d":"2013-12-06"},{"c":"00914894000125","r":"JUPITER GUARDANAPOS E PAPEIS LTDA","n":"GUARDANAPOS JUPTER","m":"GOIANIA","d":"1995-11-17"},{"c":"04164119000150","r":"JUVENAL ALVES DE SOUSA","n":"GRAFICA E EDITORA J & A","m":"CIDADE OCIDENTAL","d":"2000-10-27"},{"c":"10799234000102","r":"KAIXA INDUSTRIA E COMERCIO DE EMBALAGENS LTDA","n":"KAIXA EMBALAGENS","m":"APARECIDA DE GOIANIA","d":"2009-05-04"},{"c":"33710706000104","r":"KIKA CAKES CONFEITARIA FINA LTDA","n":"KIKA CAKES","m":"FORMOSA","d":"2019-05-23"},{"c":"38091175000124","r":"L A DOS SANTOS BRINDES CORPORATIVOS","n":"LOIHE BRINDES CORPORATIVOS","m":"APARECIDA DE GOIANIA","d":"2020-08-14"},{"c":"30195519000133","r":"L S ETIQUETAS LTDA","n":"L S ETIQUETAS","m":"GOIANIA","d":"2018-04-13"},{"c":"51857098000139","r":"L&K COMERCIAL LTDA","n":"VILA NATURAL GOIANAPOLIS","m":"GOIANAPOLIS","d":"2023-08-17"},{"c":"44289348000116","r":"LEANDRO MIRANDA DE REZENDE INDUSTRIA E COMERCIO","n":"GIRE ETIQUETAS","m":"GOIANIA","d":"2021-11-18"},{"c":"58870245000150","r":"LETICIA DE SOUSA ARAUJO AZEVEDO LTDA","n":"LETICIA ARAUJO COSMETICOS E PRESENTES","m":"ALVORADA DO NORTE","d":"2025-01-14"},{"c":"27749359000112","r":"LIDER COMUNICACAO VISUAL E GRAFICA LTDA","n":"LIDER COMUNICACAO VISUAL E GRAFICA","m":"GOIATUBA","d":"2017-05-17"},{"c":"13711686000170","r":"LIDERTEX INDUSTRIA E COMERCIO DE TINTAS E REVESTIMENTOS LTDA","n":"LIDERTEX TINTAS E REVESTIMENTOS","m":"ANAPOLIS","d":"2011-05-19"},{"c":"13711686000251","r":"LIDERTEX INDUSTRIA E COMERCIO DE TINTAS E REVESTIMENTOS LTDA","n":null,"m":"ANAPOLIS","d":"2014-05-02"},{"c":"41644940000109","r":"LILIAN R DOS SANTOS","n":"PERRI REPRESENTACOES","m":"APARECIDA DE GOIANIA","d":"2021-04-20"},{"c":"14879573000141","r":"LIRIOS ETIQUETAS E EMBALAGENS LTDA","n":"VIDEIRA EMBALAGENS","m":"GOIANIA","d":"2012-01-13"},{"c":"58787331000101","r":"LOJAS AQUI TEM INOVA SIMPLES (I.S.)","n":null,"m":"GOIANIA","d":"2025-01-11"},{"c":"22139254000128","r":"LOS BORBAS EMBALAGENS LTDA","n":"LOS BORBAS","m":"GOIANIA","d":"2015-03-27"},{"c":"44412479000149","r":"LUCIANA GOMES VILELA DE LIMA","n":"CASA CRIATIVA - ARTIGOS PARA CONFEITARIA","m":"MINEIROS","d":"2021-11-29"},{"c":"34692476000152","r":"M F ARAUJO FRASSA ALIMENTOS","n":"FRASSA ALIMENTOS","m":"QUIRINOPOLIS","d":"2019-08-28"},{"c":"32585807000120","r":"MAESTRO COMUNICACAO LTDA","n":"MAESTRO COMUNICACAO","m":"GOIANIA","d":"2019-01-28"},{"c":"37400903000170","r":"MAIS EMBALAGENS LTDA","n":"MAIS EMBALAGENS","m":"APARECIDA DE GOIANIA","d":"2020-06-13"},{"c":"07306135000129","r":"MARKA IMPRESSOS ESPECIAIS LTDA","n":"MARKA IMPRESSOS ESPECIAIS","m":"APARECIDA DE GOIANIA","d":"2005-04-05"},{"c":"56000785000157","r":"MARO PLASTIC LTDA","n":"MARO PLASTIC","m":"SAO SIMAO","d":"2024-07-19"},{"c":"67895826000137","r":"MAUGUIL SUPRIMENTOS LTDA","n":"MGS PRODUTOS PARA SUBLIMACAO","m":"GOIANIA","d":"2026-07-06"},{"c":"43182743000132","r":"MAXXI PAPEIS E EMBALAGENS LTDA","n":"MAXXI PAPEIS","m":"GOIANIA","d":"2021-08-18"},{"c":"30905511000113","r":"MEGA ETIQUETAS & ROTULOS LTDA","n":"MEGA ETIQUETAS","m":"GOIANIA","d":"2018-07-11"},{"c":"32441266000166","r":"MELHOR EMBALAGEM LTDA","n":null,"m":"APARECIDA DE GOIANIA","d":"2019-01-14"},{"c":"00641901000162","r":"MEMORIA GRAFICA E EDITORA LTDA","n":"MEMORIA GRAFICA E EDITORA","m":"INHUMAS","d":"1995-06-09"},{"c":"61243270000118","r":"MICHEL WILLIAN DE ANDRADE BARROS  LTDA","n":"ONZE IMPRESSAO","m":"RIO VERDE","d":"2025-06-10"},{"c":"44159118000132","r":"MICHEL WILLIAN DE ANDRADE BARROS 01160266182","n":null,"m":"RIO VERDE","d":"2021-11-08"},{"c":"31872648000181","r":"MIPA INDUSTRIA E COMERCIO DE MOVEIS LTDA","n":"MIPA","m":"SANTA RITA DO ARAGUAIA","d":"2018-10-26"},{"c":"13306961000251","r":"MIRAPEL -RECICLAGEM DE PAPEL LTDA","n":"MIRAPEL","m":"PORANGATU","d":"2023-09-21"},{"c":"14758929000199","r":"ML INDUSTRIA E COMERCIO DE EMBALAGENS LTDA","n":"P.O EMBALAGENS","m":"GOIANIA","d":"2011-12-13"},{"c":"05651057000174","r":"MULTPEL DISTRIBUIDORA E COMERCIO DE PAPEIS LTDA","n":"MULTPEL DO BRASIL","m":"GOIANIA","d":"2003-05-14"},{"c":"34984846000125","r":"MUNDIAL BANDEIRAS INDUSTRIA E COMERCIO LTDA","n":"MUNDIAL BANDEIRAS","m":"TRINDADE","d":"2019-09-25"},{"c":"08488731000130","r":"NASA FERRAMENTARIA E USINAGEM LTDA","n":"NASA FERRAMENTARIA E USINAGEM","m":"GOIANIA","d":"2006-11-22"},{"c":"17709385000163","r":"NATALIA ALMEIDA MOURA DE ANDRADE LTDA","n":"FABRICA DE IDEIAS","m":"GOIANESIA","d":"2013-03-07"},{"c":"33473288000170","r":"NATUCOPOS PRODUTOS LTDA","n":"NATUCOPOS","m":"NEROPOLIS","d":"2019-04-26"},{"c":"45870686000100","r":"NAZPER EMBALAGENS, INDUSTRIA E COMERCIO DE PAPEIS E EMBALAGENS LTDA","n":"NAZPER EMBALAGENS, INDUSTRIA E COMERCIO DE PAPEL","m":"LUZIANIA","d":"2022-04-01"},{"c":"58271604000152","r":"NEVESPEL INDUSTRIA E COMERCIO DE PAPEIS LTDA","n":"NEVESPEL PAPEIS","m":"ANAPOLIS","d":"2024-11-28"},{"c":"67557460000196","r":"NG GRAFICA LTDA","n":null,"m":"ANICUNS","d":"2026-06-18"},{"c":"53712753000196","r":"NILIX BRINDES E PRESENTES LTDA","n":"NILIX BRINDES E PRESENTES","m":"SANTA HELENA DE GOIAS","d":"2024-01-30"},{"c":"27516530000143","r":"NILSON PERRI","n":"GYN TUBOS","m":"APARECIDA DE GOIANIA","d":"2017-04-11"},{"c":"31801536000130","r":"NOGUEIRA E NOGUEIRA EMBALAGENS LTDA","n":"RN EMBALAGENS","m":"GOIANIA","d":"2018-10-18"},{"c":"53578221000108","r":"NOGUEIRA E VARGAS EMBALAGENS LTDA","n":"RN EMBALAGENS","m":"GOIANIA","d":"2024-01-19"},{"c":"11548000000147","r":"NOTAVEL INDUSTRIA E COMERCIO DE PAPEL LTDA","n":"NOTAVEL DISTRIBUIDORA DE PAPEL","m":"POSSE","d":"2010-02-10"},{"c":"11037897000144","r":"NOVA EMBALAGENS LTDA","n":"NOVA EMBALAGENS","m":"ANAPOLIS","d":"2009-08-07"},{"c":"49853323000117","r":"NOVA OPCAO COMUNICACAO VISUAL LTDA","n":"NOVA OPCAO GRAFICA E COMUNICACAO VISUAL","m":"GOIANIA","d":"2023-03-08"},{"c":"54947066000112","r":"NUTDAY ALIMENTOS LTDA","n":"NUTDAY","m":"GOIANIA","d":"2024-04-30"},{"c":"11015626000198","r":"NUTDAY LTDA","n":"NUTDAY","m":"GOIANIA","d":"2009-07-24"},{"c":"61188410000100","r":"O REI DO PAPELAO LTDA","n":"O REI DO PAPELAO","m":"APARECIDA DE GOIANIA","d":"2025-06-06"},{"c":"38110550000136","r":"OFFSET PAPEIS LTDA","n":"OFFSET PAPEIS","m":"GOIANIA","d":"2020-08-17"},{"c":"40953162000169","r":"OSVALDO ROSA DA SILVA 05641300101","n":null,"m":"QUIRINOPOLIS","d":"2021-02-23"},{"c":"29677156000193","r":"OX GRAFICA E EDITORA LTDA","n":"OX GRAFICA","m":"GOIANIA","d":"2018-02-14"},{"c":"59198395000121","r":"PACK GYN COMERCIO DE EMBALAGENS LTDA","n":"PACK GYN","m":"APARECIDA DE GOIANIA","d":"2025-01-30"},{"c":"41648693000100","r":"PANDA EMBALAGENS E PUBLICIDADE LTDA","n":"PANDA EMBALAGENS","m":"GOIANIA","d":"2021-04-20"},{"c":"34787822000186","r":"PAPELARIA CRIATIVA LTDA","n":"PAPELARIA CRIATIVA","m":"CAIAPONIA","d":"2019-09-06"},{"c":"39334878000107","r":"PAPELET EXPRESS LTDA","n":"PAPELET EXPRESS","m":"GOIANIA","d":"2020-10-06"},{"c":"21550447001003","r":"PARAIBUNA PAPEIS S/A","n":null,"m":"ANAPOLIS","d":"1986-02-17"},{"c":"55217568000150","r":"PATOTI INDUSTRIA DE EMBALAGENS LTDA","n":"PATOTI EMBALAGENS","m":"APARECIDA DE GOIANIA","d":"2024-05-21"},{"c":"43154234000104","r":"PAULA MARIA GARCIA MENDES 48621684187","n":"HASHTAG PRINT GRAFICA","m":"GOIANIA","d":"2021-08-17"},{"c":"37767143000133","r":"PERGAMINHOS COMERCIO E SERVICOS LTDA","n":"PERGAMINHOS","m":"FORMOSA","d":"2020-07-17"},{"c":"37925818000125","r":"PETRO SOLUCOES TECNICAS LTDA","n":"PETRO SOLUCOES TECNICAS","m":"GOIANIA","d":"2020-07-31"},{"c":"51015339000100","r":"PHABLO AUGUSTO SILVA","n":"ORIGEM AGENCIA E GRAFICA","m":"SAO LUIZ DO NORTE","d":"2023-06-12"},{"c":"33538406000181","r":"PLASTFORM IND E COM LTDA","n":"PLASTFORM EMBALAGENS","m":"GOIANIA","d":"1990-01-08"},{"c":"57388091000100","r":"PLASTMAR INDUSTRIA E COMERCIO DE EMBALAGENS LTDA","n":"PLASTMAR EMBALAGENS","m":"APARECIDA DE GOIANIA","d":"2024-09-23"},{"c":"29233571000158","r":"PLASTVIER INDUSTRIA E COMERCIO DE EMBALAGENS LTDA","n":"PLASTVIER EMBALAGENS","m":"GOIANIA","d":"2017-12-08"},{"c":"29980843000183","r":"PLAZ FORTE EMBALAGENS LTDA","n":"PLAZ FORTE EMBALAGENS","m":"LUZIANIA","d":"2018-03-20"},{"c":"44917525000323","r":"PLUS PAPEIS ESPECIAIS E EMBALAGENS LTDA","n":null,"m":"GOIANIA","d":"2024-04-17"},{"c":"01410703000150","r":"POLIGEL EMBALAGENS PLASTICAS LTDA","n":"POLIGEL","m":"GOIANIA","d":"1975-01-15"},{"c":"41709843000149","r":"POLLYANA B. P. S. LEITE LTDA","n":"ATELIE DAS CAIXAS","m":"GOIANIA","d":"2021-04-26"},{"c":"39980268000172","r":"PORTAL DOS GRAFICOS LTDA","n":null,"m":"GOIANIA","d":"2020-12-01"},{"c":"29985549000164","r":"PRINTS COMERCIO DE ETIQUETAS E SUPRIMENTOS LTDA","n":"PRINTS","m":"GOIANIA","d":"2018-03-20"},{"c":"34089697000130","r":"QUALITY PAPER BARRICAS LTDA","n":"WALL COLOR TINTAS","m":"AGUAS LINDAS DE GOIAS","d":"2019-07-02"},{"c":"28508812000161","r":"R P  CONSULTORIA GRAFICA E EDITORA LTDA","n":"GRAFICA CEMIQUE","m":"APARECIDA DE GOIANIA","d":"2017-08-25"},{"c":"01107605000149","r":"RACIONAL EMBALAGENS LTDA","n":"RACIONAL EMBALAGENS","m":"APARECIDA DE GOIANIA","d":"1996-03-21"},{"c":"40565280000108","r":"RAFAEL MEDEIROS SILVA 03281428169","n":null,"m":"ANAPOLIS","d":"2021-01-26"},{"c":"19695563000170","r":"RAQUEL SALES RAMOS CARDOSO LTDA","n":"99 EMBALAGENS","m":"GOIANIA","d":"2014-02-11"},{"c":"54856782000194","r":"RASTI EMBALAGENS PERSONALIZADAS LTDA","n":null,"m":"GOIANIA","d":"2024-04-23"},{"c":"56505446000122","r":"RB BOBINAS E ETIQUETAS LTDA","n":"RB BOBINAS E ETIQUETAS","m":"APARECIDA DE GOIANIA","d":"2024-08-12"},{"c":"58443203000132","r":"REAL COALA INDUSTRIA GRAFICA LTDA.","n":"REAL COALA INDUSTRIA GRAFICA","m":"GOIANIA","d":"2024-12-12"},{"c":"11803100000172","r":"REGINA BORGES MACHADO 78183049168","n":null,"m":"GOIANIA","d":"2010-04-12"},{"c":"52459299000140","r":"REMMACK EMBALAGENS PLASTICAS FLEXIVEIS LTDA","n":"REMMACK","m":"ANAPOLIS","d":"2023-10-06"},{"c":"07163516000104","r":"REMMACK FILMS INDUSTRIA E COMERCIO LTDA","n":"REMMACK FILMS","m":"ANAPOLIS","d":"2005-01-06"},{"c":"39519250000178","r":"RENA EMBALAGENS LTDA","n":"AZURE PACK","m":"GOIANIA","d":"2020-10-22"},{"c":"30256575000130","r":"RESERVA GRAFICA E EDITORA LTDA","n":"GRAFICA INFINITY","m":"GOIANIA","d":"2018-04-20"},{"c":"24888298000186","r":"REVO COMUNICACAO VISUAL LTDA","n":"AGENCIA REVO","m":"FORMOSA","d":"2016-05-29"},{"c":"40390458000119","r":"RJ ATACADO DISTRIBUIDORA LTDA","n":"RJ ATACADO DISTRIBUIDORA","m":"APARECIDA DE GOIANIA","d":"2021-01-14"},{"c":"65027989000415","r":"ROLLPACK INDUSTRIA E COMERCIO DE PLASTICOS E PAPEL LTDA.","n":"ROLLPACK GOIANIA","m":"GOIANIA","d":"2023-07-07"},{"c":"22516388000110","r":"RRC EMBALAGENS LTDA","n":"CANDIDO EMBALAGENS","m":"ANAPOLIS","d":"2015-05-22"},{"c":"55132691000179","r":"RS MARQUES SERVICOS E REFORMAS LTDA","n":"MSOUZA SERVICOS","m":"VALPARAISO DE GOIAS","d":"2024-05-15"},{"c":"13477064000120","r":"RUAS INDUSTRIA, COMERCIO E SERVICOS LTDA","n":"TRIPOLI GUARDANAPOS E SACHES","m":"GOIANIA","d":"2011-04-04"},{"c":"26304462000196","r":"S P DOS SANTOS TURONES BRINDES PERSONALIZADOS LTDA","n":"SANTTIS BRINDES","m":"GOIANIA","d":"2016-10-06"},{"c":"42843783000115","r":"SANPLASTIC INDUSTRIA DE EMBALAGENS LIMITADA","n":"SANPLASTIC","m":"GOIANIA","d":"2021-07-23"},{"c":"37395852000135","r":"SEDDAS GUARDANAPOS E PAPEIS LTDA","n":"SEDDAS GUARDANAPOS","m":"GOIANIA","d":"1992-10-13"},{"c":"52129471000106","r":"SERVING SOLLUTY LTDA","n":null,"m":"AGUAS LINDAS DE GOIAS","d":"2023-09-11"},{"c":"07961414000126","r":"SKYMILHO INDUSTRIA E COMERCIO DE ALIMENTOS LTDA","n":"PANCHITOS","m":"GOIANIA","d":"2006-04-24"},{"c":"67502787000160","r":"SMART CRACHAS INTELIGENTES PERSONALIZADOS LTDA","n":"SMART CRACHAS","m":"GOIANIA","d":"2026-06-10"},{"c":"37469406000128","r":"SMART GRAFICA COMUNICACAO LTDA","n":"SMART GRAFICA E COMUNICACAO","m":"TRINDADE","d":"2020-06-19"},{"c":"45372417000113","r":"SOLUCOES ACABAMENTOS LTDA","n":"SOLUCOES ACABAMENTOS","m":"GOIANIA","d":"2022-02-21"},{"c":"45698023000150","r":"SOUZA E VALE IND E COMERCIO LTDA","n":"UCAL","m":"GOIANIA","d":"2022-03-18"},{"c":"10255980000127","r":"STARPEL - INDUSTRIA E COMERCIO LTDA","n":"STARPEL","m":"APARECIDA DE GOIANIA","d":"2008-08-07"},{"c":"54468985000103","r":"STIK UNIPESSOAL LTDA","n":"STIK FITNESS","m":"CATALAO","d":"2024-03-25"},{"c":"38487175000148","r":"STOCK DIGITAL LTDA","n":"STOCK DIGITAL","m":"GOIANIA","d":"2020-09-16"},{"c":"24831465000152","r":"TATIANE CRISTINA RODRIGUES 99679140172","n":null,"m":"GOIANIA","d":"2016-05-18"},{"c":"35327926000170","r":"TAYME FLEX ETIQUETAS LTDA","n":"TAYME FLEX ETIQUETAS","m":"APARECIDA DE GOIANIA","d":"2019-10-28"},{"c":"53528649000146","r":"TELARIUM INDUSTRIA E COMERCIO DE PAPEIS LTDA","n":"M3 PAPEIS","m":"GOIANIA","d":"2024-01-17"},{"c":"33336328000132","r":"THAINAR CESAR PEREIRA 06627033160","n":null,"m":"VALPARAISO DE GOIAS","d":"2019-04-11"},{"c":"50162110000128","r":"TOQUE MAGICO DIGITAL & GRAFICA LTDA","n":null,"m":"VALPARAISO DE GOIAS","d":"2023-03-31"},{"c":"46362510000100","r":"TS COMERCIO E SERVICOS LTDA","n":"LIA MARMITARIA","m":"TRINDADE","d":"2022-05-12"},{"c":"44313678000108","r":"UNIQUE FESTAS LTDA","n":"ATELIE DANUBIA RODRIGUES","m":"GOIANIA","d":"2021-11-20"},{"c":"05991789000103","r":"VAZ & CORDEIRO INDUSTRIA E COMERCIO DE EMBALAGENS LTDA","n":"UNIPEL INDUSTRIA DE EMBALAGENS","m":"ABADIA DE GOIAS","d":"2003-11-17"},{"c":"05991789000294","r":"VAZ & CORDEIRO INDUSTRIA E COMERCIO DE EMBALAGENS LTDA","n":"UNIPEL INDUSTRIA DE EMBALAGENS","m":"GOIANIA","d":"2009-02-16"},{"c":"61434472000147","r":"VB ETIQUETAS E SUPRIMENTOS LTDA","n":"VB ETIQUETAS","m":"GOIANIA","d":"2025-06-24"},{"c":"23913576000145","r":"VENERO EMBALAGENS LTDA","n":"VENERO EMBALAGENS","m":"RIO VERDE","d":"2016-01-05"},{"c":"15175304000167","r":"VILAIFE PERSONALIZADOS LTDA","n":"VILAIFE PERSONALIZADOS","m":"PORANGATU","d":"2012-03-12"},{"c":"30688583000156","r":"VIP ASSESSORIA COMERCIO E DISTRIBUICAO LTDA","n":"VIP ASSESSORIA COMERCIO E DISTRIBUICAO","m":"MINACU","d":"2018-06-13"},{"c":"32011573000107","r":"VISOPEL COMERCIO E INDUSTRIALIZACAO DE EMBALAGENS LTDA","n":"VISOPEL EMBALAGENS","m":"VALPARAISO DE GOIAS","d":"2018-11-13"},{"c":"54734052000110","r":"VITA EMBALAGENS DE PAPEL LTDA","n":"VITA INDUSTRIA DE EMBALAGENS DE PAPEL","m":"GOIANIA","d":"2024-04-15"},{"c":"32043355000154","r":"VITAPACK INDUSTRIA DE EMBALAGENS LTDA","n":"VITAPACK","m":"GOIANIA","d":"2018-11-19"},{"c":"03535280000120","r":"VITEZZA INDUSTRIA LTDA","n":null,"m":"ITUMBIARA","d":"1999-11-25"},{"c":"13954101000143","r":"VOPRIX IMPRESSOS PERSONALIZADOS LTDA","n":"VOPRIX GRAFICA","m":"GOIANIA","d":"2011-07-14"}]