[{"c":"11872062000100","r":"11.872.062 DIVANIO BRANDAO CARDOSO","n":null,"m":"GOIAS","d":"2010-04-28"},{"c":"33406615000171","r":"33.406.615 GUSTAVO HENRIQUE ALVES ALMEIDA","n":null,"m":"GOIANIA","d":"2019-04-19"},{"c":"38429922000191","r":"38.429.922 KAROLLINE PAOLLA JORGE","n":null,"m":"GOIANIA","d":"2020-09-11"},{"c":"41688299000104","r":"41.688.299 GESSICA NAYARA DA SILVA","n":null,"m":"SENADOR CANEDO","d":"2021-04-23"},{"c":"48280444000154","r":"48.280.444 SANDRA CAMILA DE PAULA LOPES","n":null,"m":"VALPARAISO DE GOIAS","d":"2022-10-13"},{"c":"51785869000120","r":"51.785.869 VALDECI NUNES DA SILVA","n":null,"m":"GOIANIA","d":"2023-08-11"},{"c":"57515175000159","r":"57.515.175 WILSON CORREIA DA SILVA","n":null,"m":"GOIANIA","d":"2024-10-01"},{"c":"58522163000114","r":"AF & HR RODRIGUES LTDA","n":"A LAVANDERIA DE TENIS CERRADO","m":"RIO VERDE","d":"2024-12-19"},{"c":"36859569000154","r":"AGT AGROPET LTDA","n":"AGT AGROPET","m":"APARECIDA DE GOIANIA","d":"1991-06-14"},{"c":"33964986000179","r":"ALEX MARTINS LEMOS DA SILVA","n":"NOVA AGRO","m":"NOVA GLORIA","d":"2019-06-18"},{"c":"29514483000124","r":"AMPLA COMERCIO SERVICOS CONSTRUCOES E INCORPORADORA LTDA","n":"AMPLA COMERCIO SERVICOS CONSTRUCOES E INCORPORADORA","m":"VALPARAISO DE GOIAS","d":"2018-01-24"},{"c":"30413060000105","r":"ANDRE LUIS ALMEIDA RAPOSO","n":"TOPONEW EQUIPAMENTOS GEOELETRONICOS","m":"GOIANIA","d":"2018-05-09"},{"c":"52258138000270","r":"ARAGUATI LUGGAGE BOLSAS E ACESSORIOS LTDA","n":null,"m":"GOIANIA","d":"2024-01-11"},{"c":"52258138000199","r":"ARAGUATI LUGGAGE BOLSAS E ACESSORIOS LTDA","n":null,"m":"APARECIDA DE GOIANIA","d":"2023-09-20"},{"c":"47837838000106","r":"ARRUDA INDUSTRIA E COMERCIO DE CALCADOS LTDA","n":"ARRUDA CALCADOS","m":"GOIANIA","d":"2022-09-05"},{"c":"42726435000168","r":"ATR BRAND COMERCIO LTDA","n":"ATR BRAND","m":"GOIANIA","d":"2021-07-15"},{"c":"02576283000140","r":"B & V ARTES E ASSESSORIOS EM COUROS LTDA","n":"B & V ARTES EM COURO","m":"GOIANIA","d":"1998-05-01"},{"c":"51295524000198","r":"BOOT WEAR INDUSTRIA DE CALCADOS LTDA","n":"BOOT WEAR INDUSTRIA DE CALCADOS","m":"ANAPOLIS","d":"2023-07-04"},{"c":"59876544000164","r":"BRAZA MOTOS LTDA","n":"BRAZA MOTOS","m":"AGUAS LINDAS DE GOIAS","d":"2025-03-13"},{"c":"52132786000102","r":"CASSIANO CAPAS COMERCIO E SERVICOS LTDA","n":"CASSIANO CAPAS COMERCIO E SERVICOS","m":"TRINDADE","d":"2023-09-11"},{"c":"05310207000186","r":"CENTRAL DE SERVICOS COMERCIO E ALIMENTACAO LTDA","n":"SAPATARIA DO FUTURO","m":"GOIANIA","d":"2002-10-02"},{"c":"41339082000180","r":"CLAUDENIR MORALES DE SOUZA SANDALIARIA CATALAO","n":"SANDALIARIA CATALAO","m":"CATALAO","d":"2021-03-24"},{"c":"58087036000134","r":"CLEAN PLUS LAVANDERIA LTDA","n":"CLEAN PLUS LAVANDERIA","m":"GOIANIA","d":"2024-11-13"},{"c":"23759842000127","r":"CLEIDE DA SILVA QUIXABEIRA TRISTAO LTDA","n":"POTENCIA COUROS","m":"GOIANIA","d":"2015-11-27"},{"c":"34425508000153","r":"COMERCIAL CERRADO BRASIL COMERCIO, SERVICOS E REPRESENTACAO LTDA","n":"COMERCIAL CERRADO BRASIL","m":"GOIANIA","d":"2019-08-05"},{"c":"02167552000114","r":"COMERCIAL ROCHA GR LTDA","n":"COMERCIAL ROCHA GR","m":"FORMOSA","d":"1997-10-02"},{"c":"66440000000110","r":"DANI GRAZI ATACADISTA LTDA","n":"DANI GRAZI ATACADISTA","m":"ANAPOLIS","d":"2026-04-24"},{"c":"62161887000157","r":"DANIEL SERVICOS DE COSTURA GOIANIA LTDA","n":"ARRANJOS EXPRESS","m":"GOIANIA","d":"2025-08-11"},{"c":"26903336000158","r":"DELTA EMPREENDIMENTOS LTDA","n":"DELTA EMPREENDIMENTOS","m":"LUZIANIA","d":"1991-04-02"},{"c":"44416660000123","r":"DELTA LAVANDERIA E SERVICOS LTDA","n":"DELTA LAVANDERIA","m":"CRISTALINA","d":"2021-11-29"},{"c":"45909225000101","r":"DOIS DONOS CALCADOS LTDA","n":"DOIS DONOS CALCADOS","m":"GOIANIA","d":"2022-04-05"},{"c":"28471848000118","r":"EDGAR ZANETTI 02865121810","n":null,"m":"RIO VERDE","d":"2017-08-22"},{"c":"34887960000137","r":"EDSON SOARES 47869526134","n":null,"m":"GOIANIA","d":"2019-09-16"},{"c":"52775019000103","r":"ELEGANCE NETWORK EMPRESARIAL LTDA","n":"ELEGANCE NETWORK EMPRESARIAL","m":"GOIANIA","d":"2023-11-04"},{"c":"12442790000144","r":"ELI FERREIRA DA SILVA 42280150182","n":null,"m":"CRIXAS","d":"2010-08-26"},{"c":"08328665000130","r":"ELIZIARIO D.M. DA SILVA CLINICA DO TENIS","n":"CLINICA DO TENIS","m":"GOIANIA","d":"2006-09-25"},{"c":"21550353000135","r":"ESPERANCA CALCADOS LTDA","n":null,"m":"GOIANIA","d":"2014-12-11"},{"c":"10273231000122","r":"EXECUTIVA TRANSPORTES TURISMO SERVICOS E COMERCIO LTDA","n":"MAXMA OFICINA DAS MALAS","m":"GOIANIA","d":"2008-08-15"},{"c":"53447296000150","r":"FAZ TUDO COMERCIO E SERVICOS LTDA","n":"FAZ TUDO COMERCIO E SERVICOS","m":"GOIANIA","d":"2024-01-10"},{"c":"53869167000150","r":"FBK2G LAVAGENS E SERVICOS LTDA","n":"DRYCLEAN USA GOIANIA","m":"GOIANIA","d":"2024-02-09"},{"c":"43995300000160","r":"FERREIRA & PRADO EMPRESARIAL LTDA","n":"SELARIA PRADO","m":"GOIANIA","d":"2021-10-25"},{"c":"53340885000134","r":"FLAMBOYANT COMERCIO VAREJISTA DE ACESSORIOS DE VIAGENS LTDA","n":null,"m":"GOIANIA","d":"2024-01-02"},{"c":"55741592000194","r":"FLOW FITNESS LTDA","n":"FLOW FITNESS","m":"GOIANIA","d":"2024-07-01"},{"c":"51748494000128","r":"FRANCA COMERCIAL COMERCIO E SERVICOS LTDA","n":"FAZ TUDO COMERCIO E SERVICOS","m":"GOIANIA","d":"2023-08-09"},{"c":"40236557000140","r":"GABRIEL RODRIGUES ROMEIRO 00935567135","n":null,"m":"GOIANIA","d":"2021-01-03"},{"c":"10347517000105","r":"GDFZ-COMERCIO E SERVICOS DE RENOVACAO DE BOLSAS E ACESSORIOS LTDA","n":"PONTO CRIATIVO","m":"ANAPOLIS","d":"2008-09-08"},{"c":"64197680000168","r":"GERALDINI CONSULTORIA LTDA","n":null,"m":"GOIANIA","d":"2025-12-29"},{"c":"44925443000169","r":"GILVAN CARLOS PEREIRA 81301790168","n":null,"m":"TRINDADE","d":"2022-01-19"},{"c":"30009495000180","r":"GOLD COMERCIO LTDA","n":"GOLD","m":"TRINDADE","d":"2018-03-22"},{"c":"49557041000172","r":"GYN VAREJAO E CALCADOS LTDA","n":"GYN VAREJAO E CALCADOS","m":"APARECIDA DE GOIANIA","d":"2023-02-10"},{"c":"51011845000113","r":"HEXACTA LTDA","n":null,"m":"ITABERAI","d":"2023-06-12"},{"c":"61428779000135","r":"HM MALAS E BOLSAS LTDA","n":"HOSPITAL DAS MALAS LTDA","m":"GOIANIA","d":"2025-06-24"},{"c":"57737903000177","r":"HOME DECOR LTDA","n":"HOME DECOR","m":"QUIRINOPOLIS","d":"2024-10-17"},{"c":"13169524000152","r":"HOSPITAL DAS MALAS LTDA","n":null,"m":"GOIANIA","d":"2011-01-28"},{"c":"39778680000104","r":"HUGO H L GONCALVES","n":"SH SHOES","m":"GOIANIA","d":"2020-11-13"},{"c":"57409714000175","r":"ILM INDUSTRIA E COMERCIO DE CALCADOS ARTESANAL LTDA","n":null,"m":"TRINDADE","d":"2024-09-24"},{"c":"36857548000108","r":"INDUSTRIA E COMERCIO DE CALCADOS ROGGER LTDA","n":"ANA CAROLINA FASHION","m":"PARANAIGUARA","d":"1991-06-13"},{"c":"36217536000100","r":"JEFFERSON MARTINS SILVA 79860184100","n":null,"m":"TRINDADE","d":"2020-02-01"},{"c":"42915117000307","r":"JM SERVICOS DE VESTUARIO LTDA","n":null,"m":"GOIANIA","d":"2022-11-28"},{"c":"42915117000145","r":"JM SERVICOS DE VESTUARIO LTDA","n":null,"m":"GOIANIA","d":"2021-07-29"},{"c":"36808516000104","r":"JOAO BATISTA SANTOS GIANVECCHIO 73654396100","n":null,"m":"GOIANIA","d":"2020-03-30"},{"c":"37345733000178","r":"JOAO CARLOS VIEIRA","n":null,"m":"GOIANIA","d":"1992-05-27"},{"c":"04828751000151","r":"JOSE AUGUSTO GUGEL","n":"GUGEL ESTOFADOS","m":"POSSE","d":"2001-10-25"},{"c":"36670045000110","r":"JULIANO MOREIRA 00891156194","n":null,"m":"ANAPOLIS","d":"2020-03-13"},{"c":"12259977000107","r":"JULIO CESAR DOS SANTOS 80314740368","n":null,"m":"GOIANIA","d":"2010-07-21"},{"c":"27737932000178","r":"KENYA MENDONCA LTDA","n":"SPLENDA CALCADOS","m":"GOIANIA","d":"2017-05-15"},{"c":"01003110000170","r":"LAVANDERIA CISLAV LTDA","n":"CISLAV LAVANDERIAS","m":"GOIANIA","d":"1984-10-22"},{"c":"01003110000927","r":"LAVANDERIA CISLAV LTDA","n":"CISLAV LAVANDERIAS","m":"GOIANIA","d":"2017-01-16"},{"c":"44161629000199","r":"LAVANDERIA DELIVERY E SERVICOS LTDA","n":"SAPATARIA DO FUTURO","m":"GOIANIA","d":"2021-11-08"},{"c":"33404104000110","r":"LELIO FREITAS CAMARGOS","n":"SAPATARIA PROGRESSO","m":"MINEIROS","d":"1989-10-26"},{"c":"43232314000122","r":"LETYCIA CLOSET LTDA","n":"LETYCIA CLOSET","m":"GOIANIA","d":"2021-08-23"},{"c":"33671275000106","r":"LICICOM COMERCIO E SERVICOS LTDA","n":"LICICOM DIGITAL","m":"VALPARAISO DE GOIAS","d":"2019-05-21"},{"c":"49960082000105","r":"LOURENCO BORGES LAVANDERIA LTDA","n":"RESTAURA JEANS","m":"CATALAO","d":"2023-03-16"},{"c":"55870219000133","r":"LUANA RESENDE SILVA  LTDA","n":"MINHA LAVANDERIA MINEIROS","m":"MINEIROS","d":"2024-07-10"},{"c":"00067983000183","r":"LUNA CONFECCOES LTDA","n":"LUNA CONFECCOES","m":"JARAGUA","d":"1982-05-05"},{"c":"32331472001608","r":"LVMH FASHION GROUP BRASIL LTDA.","n":null,"m":"GOIANIA","d":"2017-07-06"},{"c":"24471589000174","r":"M J C MENDES","n":"BELA FEMME SHOES","m":"TRINDADE","d":"2016-03-29"},{"c":"67506743000109","r":"M V A REPAROS LTDA","n":"M V A REPAROS","m":"GOIANESIA","d":"2026-06-16"},{"c":"15178216000119","r":"MARCOS GONCALVES DE SOUSA 87385384153","n":null,"m":"GOIANIA","d":"2012-03-12"},{"c":"15569498000347","r":"MARCOS VINICIUS MOREIRA LIMA","n":null,"m":"ITAGUARU","d":"2020-08-20"},{"c":"15569498000266","r":"MARCOS VINICIUS MOREIRA LIMA","n":null,"m":"SANCLERLANDIA","d":"2020-08-20"},{"c":"31659095000183","r":"MARCUS VINICIUS DA SILVA 55650260168","n":null,"m":"ITUMBIARA","d":"2018-10-02"},{"c":"36608951000195","r":"MARYSHOES67 LTDA","n":"MARYSHOES67","m":"GOIANIA","d":"2020-03-09"},{"c":"15242115000160","r":"MAURICIO CURADO CARVALHO FRANCO LTDA","n":"SAPATARIA DO FUTURO","m":"GOIANIA","d":"2012-03-22"},{"c":"43836126000103","r":"MEGA SOLA COMERCIO DE SOLADOS LTDA","n":"MEGA SOLA","m":"GOIANIA","d":"2021-10-11"},{"c":"51815234000128","r":"METTA CALCADOS E SELARIA LTDA","n":"METTA CALCADOS E SELARIA","m":"SILVANIA","d":"2023-08-15"},{"c":"39915156000138","r":"MIRIAM RODRIGUES DE OLIVEIRA 02970559331","n":null,"m":"ANAPOLIS","d":"2020-11-25"},{"c":"57991590000189","r":"MORENO & TURONES BOLSAS E MOCHILAS LTDA","n":"M & T","m":"GOIANIA","d":"2024-11-06"},{"c":"42229920000126","r":"MOVELARIA CERRADO LTDA","n":"MOVELARIA CERRADO","m":"AGUAS LINDAS DE GOIAS","d":"2021-06-07"},{"c":"48901324000127","r":"MRA MOCHILAS E BOLSAS LTDA","n":"MRA MOCHILAS E BOLSAS","m":"GOIANIA","d":"2022-12-15"},{"c":"39435852000147","r":"N L SERVICOS DE LAVANDERIA LTDA","n":"NOVA LAVANDERIA","m":"GOIANIA","d":"2020-10-15"},{"c":"27605411000167","r":"NOVA OPCAO SAPATARIA LTDA","n":null,"m":"GOIANIA","d":"2017-04-26"},{"c":"02815645000108","r":"OSMAR RIBEIRO DE SOUSA","n":"STILLUS","m":"GOIANIA","d":"1986-10-01"},{"c":"22284789000192","r":"PABLO SOCRATES DE BRITO 89260325153","n":null,"m":"GOIANIA","d":"2015-04-18"},{"c":"54947097000173","r":"PASSEIO DAS AGUAS MALAS E ACESSORIOS LTDA","n":null,"m":"GOIANIA","d":"2024-04-30"},{"c":"17192364000113","r":"PAULO CAMILO PINHEIRO","n":null,"m":"ANICUNS","d":"2012-11-21"},{"c":"22739906000165","r":"PAULO CESAR DIAS COSTA 41281543187","n":null,"m":"TRINDADE","d":"2015-06-29"},{"c":"50233846000140","r":"PEREIRA E PEREIRA REPRESENTACOES LTDA","n":"PEREIRA E PEREIRA REPRESENTACOES","m":"CERES","d":"2023-04-06"},{"c":"13441098000164","r":"R BOOT INDUSTRIA E COMERCIO DE CALCADOS LTDA","n":"NICOLAS CALCADOS","m":"APARECIDA DE GOIANIA","d":"2011-03-29"},{"c":"18932687000169","r":"R. S. QUEIROZ - CORTES","n":"RH CORTES","m":"GOIANIA","d":"2013-09-12"},{"c":"37844015000146","r":"RACA INDUSTRIA E COMERCIO LTDA","n":"RACA BOOTS","m":"ANAPOLIS","d":"2020-07-24"},{"c":"30994188000100","r":"RAFFINATO DESIGN ESTOFADOS E MOVEIS LTDA","n":"SOTTILE DESIGN","m":"GOIANIA","d":"2018-07-23"},{"c":"01013815000178","r":"RAPIDINHO RENOVADORA DE CALCADOS LTDA","n":null,"m":"GOIANIA","d":"1996-01-23"},{"c":"18423860000101","r":"RAQUEL ARAUJO DOS SANTOS NASCIMENTO","n":"RAQUEL ATELIE","m":"SANTA HELENA DE GOIAS","d":"2013-07-04"},{"c":"50215354000121","r":"RDS DRONE SERVICE LTDA","n":null,"m":"CATALAO","d":"2023-04-05"},{"c":"55535998000110","r":"RIBEIRO COMERCIO E EQUIPAMENTOS LTDA","n":"RIBEIRO COMERCIO E EQUIPAMENTOS","m":"GOIANIA","d":"2024-06-14"},{"c":"17963493000168","r":"RICK DONALVAN DA SILVA RICARTE PEREIRA 01874997136","n":null,"m":"ANAPOLIS","d":"2013-04-18"},{"c":"52258626000104","r":"RIO VERDE PRESENTES E ACESSORIOS LTDA","n":null,"m":"RIO VERDE","d":"2023-09-20"},{"c":"35305987000137","r":"ROBERTO SOARES DE AZEVEDO 01487757131","n":null,"m":"APARECIDA DE GOIANIA","d":"2019-10-24"},{"c":"40571501000142","r":"RODRIGO MORAIS DE PAIVA 00345600177","n":null,"m":"GOIANIA","d":"2021-01-26"},{"c":"54297165000104","r":"ROSARIO DIAS COMPONENTES PARA CALCADOS LTDA","n":"INOVAR COMPONENTES PARA CALCADOS","m":"GOIANIA","d":"2024-03-12"},{"c":"54964464000147","r":"ROSI MODA FEMININA LTDA","n":"ROSI MODA FEMININA","m":"GOIANIA","d":"2024-05-02"},{"c":"43555019000107","r":"RUBER PAULO CAMELO DOS SANTOS 03383158101","n":null,"m":"GOIANIA","d":"2021-09-17"},{"c":"52317397000143","r":"SANDALIARIA GOIANIA LTDA","n":"SANDALIARIA GOIANIA","m":"GOIANIA","d":"2023-09-26"},{"c":"04985325000121","r":"SAPATARIA AEROPORTO LTDA","n":"SAPATARIA AEROPORTO","m":"MORRINHOS","d":"2002-04-04"},{"c":"60916410000109","r":"SAPATARIA DELIVERY E SERVICOS LTDA","n":"SAPATARIA DO FUTURO","m":"GOIANIA","d":"2025-05-20"},{"c":"81875601000140","r":"SAPATARIA GYN LTDA","n":"SAPATARIA GYN","m":"GOIANIA","d":"1990-06-18"},{"c":"62679044000147","r":"SAPATARIA ROMANOS LTDA","n":"SAPATARIA ROMANOS","m":"GOIANIA","d":"2025-09-11"},{"c":"13918259000168","r":"SAPATEIRO NIQUELANDIA LTDA","n":"SAPATEIRO NIQUELANDIA","m":"NIQUELANDIA","d":"2011-07-05"},{"c":"06347409007259","r":"SBF COMERCIO DE PRODUTOS ESPORTIVOS S.A.","n":"CENTAURO","m":"GOIANIA","d":"2008-07-25"},{"c":"06347409011523","r":"SBF COMERCIO DE PRODUTOS ESPORTIVOS S.A.","n":"CENTAURO","m":"APARECIDA DE GOIANIA","d":"2008-09-03"},{"c":"50667205000101","r":"SELECT SHOES DETAIL LTDA","n":"SELECT SNEAKERS","m":"GOIANIA","d":"2023-05-15"},{"c":"60091100000100","r":"SERGI ROMERO FABRICA LTDA","n":"SERGI ROMERO","m":"SANCLERLANDIA","d":"2025-03-26"},{"c":"22917190000149","r":"SIDNEY CAMPOS DA SILVA 47828676115","n":null,"m":"GOIANIA","d":"2015-07-23"},{"c":"51267396000179","r":"TATY MORENA CALCADOS LTDA","n":"TATY MORENA CALCADOS","m":"GOIANIRA","d":"2023-07-03"},{"c":"18525586000173","r":"TAVITA COUROS COMERCIO E INDUSTRIA LTDA","n":"CHAPEU & CIA","m":"GOIANIA","d":"2013-07-19"},{"c":"34738710000135","r":"TEIXEIRA PEREIRA COMERCIO E INDUSTRIA DE ARTIGOS DE COURO LTDA","n":"CHAPEU E CIA","m":"GOIANIA","d":"2019-09-02"},{"c":"39781537000171","r":"TEMPO LIVRE LAVANDERIAS LTDA","n":"MINHA LAVANDERIA GOIANIA","m":"GOIANIA","d":"2020-11-13"},{"c":"42548082000587","r":"TEXTILE XTRA CO. LTDA","n":"TXC","m":"GOIANIA","d":"2023-03-02"},{"c":"42548082000153","r":"TEXTILE XTRA CO. LTDA","n":"TXC","m":"GOIANIA","d":"2021-07-01"},{"c":"04104676000933","r":"TIFFANY-BRASIL LTDA","n":null,"m":"GOIANIA","d":"2025-01-21"},{"c":"22104520000187","r":"TRAMA DESIGN E ARQUITETURA LTDA","n":"TRAMA DESIGN","m":"GOIANIA","d":"2015-03-23"},{"c":"42464104000105","r":"V E M COMERCIO E DISTRIBUICAO LTDA","n":"V E M COMERCIO","m":"FORMOSA","d":"2021-06-24"},{"c":"09347355000126","r":"V E V SERVICOS LTDA","n":"RENASCER SERVICOS","m":"VICENTINOPOLIS","d":"2007-12-28"},{"c":"36837362000189","r":"VALDECI OLIVEIRA DE ARRUDA 29153751191","n":null,"m":"ANAPOLIS","d":"2020-04-01"},{"c":"23944186000132","r":"VALDIVINO LUCIANO DE SOUZA FILHO 87715660159","n":null,"m":"ANICUNS","d":"2016-01-11"},{"c":"20228668000106","r":"VALMIR LIMIRO DA SILVA","n":"SAPATARIA OLIMPICA","m":"APARECIDA DE GOIANIA","d":"2014-05-12"},{"c":"37610629000163","r":"VANDERSILVO PEREIRA DE OLIVEIRA 06174633101","n":null,"m":"CAMPOS BELOS","d":"2020-07-03"},{"c":"30689748000104","r":"VANIA MARTINS DE SENA 92579230297","n":null,"m":"GOIANIA","d":"2018-06-13"},{"c":"16003147000175","r":"VILMAR RODRIGUES DE MENEZES","n":"SAPATARIA MENEZES","m":"GOIANIA","d":"1988-05-27"},{"c":"26741539000195","r":"VIVA SHOES INDUSTRIA E COMERCIO DE CALCADOS LTDA","n":"VIVA","m":"GOIANIA","d":"2016-12-20"},{"c":"35493502000186","r":"WR SERVICOS DE LAVANDERIA LTDA","n":"NOVA LAVANDERIA","m":"GOIANIA","d":"2019-11-12"},{"c":"17027090000107","r":"WSB ROUPAS E ACESSORIOS LTDA","n":"WSB ROUPAS","m":"GOIANIA","d":"2012-10-18"},{"c":"15238429000199","r":"XAVIER & MENESES LAVANDERIA LTDA","n":"CLEAN LAVANDERIA","m":"GOIANIA","d":"2012-03-21"}]