[{"c":"27284452000107","r":"27.284.452 MARIANNE CARVALHO DE SOUZA PAZ","n":null,"m":"GOIANIA","d":"2017-03-13"},{"c":"52694600000109","r":"2A SERVICOS DE DIAGNOSTICOS LABORATORIAIS LTDA","n":"EXATO LABORATORIO","m":"FORMOSA","d":"2023-10-27"},{"c":"30871730000129","r":"30.871.730 SILVIO JUNIO GOMES DE MELO","n":null,"m":"GOIANIA","d":"2018-07-06"},{"c":"37680396000175","r":"37.680.396 ZULEIDE DOS SANTOS","n":null,"m":"ABADIA DE GOIAS","d":"2020-07-10"},{"c":"39572793000159","r":"39.572.793 RICARDO HENRIQUE DE OLIVEIRA","n":null,"m":"APARECIDA DE GOIANIA","d":"2020-10-27"},{"c":"42253009000154","r":"42.253.009 UELLINGTON LUIZ DOS SANTOS","n":null,"m":"GOIATUBA","d":"2021-06-09"},{"c":"43240575000194","r":"43.240.575 ALESSANDRA CAETANO DA SILVA COSTA","n":null,"m":"JOVIANIA","d":"2021-08-23"},{"c":"46023591000113","r":"46.023.591 EDIANA RODRIGUES DE SOUZA","n":null,"m":"PORANGATU","d":"2022-04-13"},{"c":"48245192000122","r":"48.245.192 JAKSON RODRIGUES RIBEIRO","n":null,"m":"HIDROLANDIA","d":"2022-10-10"},{"c":"49500362000130","r":"49.500.362 ELISANGELA SOARES DE OLIVEIRA","n":null,"m":"CERES","d":"2023-02-07"},{"c":"50342394000134","r":"50.342.394 JALES DIAS DE MELO FILHO","n":null,"m":"MORRINHOS","d":"2023-04-17"},{"c":"59535685000113","r":"59.535.685 KARINE DE OLIVEIRA","n":null,"m":"GOIANIA","d":"2025-02-18"},{"c":"60859060000196","r":"60.859.060 SILVERIO HENRIQUE HASTENREITER FILHO","n":"LAVANDERIA VALPARAISO SERVICOS EXPRESSOS LTDA","m":"VALPARAISO DE GOIAS","d":"2025-05-16"},{"c":"54119803000199","r":"A F S BIZERRA","n":"LAVANDERIA CARVALHO","m":"LUZIANIA","d":"2024-02-29"},{"c":"07888101000190","r":"A M DOMENEGHETTI","n":"CENTRAL LOCACAO","m":"GOIANIA","d":"2006-03-16"},{"c":"15188822000115","r":"A SETE COMERCIO E SERVICOS LTDA","n":"A SETE COMERCIO E SERVICOS","m":"GOIANIA","d":"2011-11-28"},{"c":"25058007000195","r":"ACAO ASSESSORIA & GESTAO EMPRESARIAL LTDA","n":"LF CONDOMINIOS","m":"CALDAS NOVAS","d":"2016-06-22"},{"c":"48942371000119","r":"ADRIELLY M RODOVALHO LAVANDERIAS LTDA","n":"LAVO MINEIROS","m":"MINEIROS","d":"2022-12-20"},{"c":"09498019000346","r":"ADRIENE APARECIDA DA COSTA BARROS","n":"LAVANDERIA A2","m":"CATALAO","d":"2022-11-29"},{"c":"58522163000114","r":"AF & HR RODRIGUES LTDA","n":"A LAVANDERIA DE TENIS CERRADO","m":"RIO VERDE","d":"2024-12-19"},{"c":"21432520000143","r":"AGIPLAN SERVICOS LTDA","n":"AGIPLAN SERVICOS","m":"OUVIDOR","d":"2014-11-18"},{"c":"52178635000187","r":"AGUIA EMPREENDIMENTOS FLORESTAIS INDUSTRIAIS E COMERCIO LTDA","n":"AGUIA EMPREENDIMENTOS FLORESTAIS INDUSTRIAIS E COMERCIO","m":"CRISTALINA","d":"2023-09-14"},{"c":"18890734000159","r":"ALEXANDRE MILHOMEM DOS SANTOS DECORACAO DE INTERIORES LTDA","n":"AM CASA","m":"GOIANIA","d":"2013-09-17"},{"c":"24947405000108","r":"ALEXSANDRO CAMPOS SILVA","n":"TUDO A SECO","m":"GOIANIA","d":"2016-06-07"},{"c":"51283808000164","r":"ALFA DIESEL LTDA","n":"ALFA TRUCK CENTER","m":"ANAPOLIS","d":"2023-07-04"},{"c":"34778284000163","r":"ALISSON FRANCISCO DA SOLIDADE SANTOS 01601475306","n":null,"m":"GOIANIA","d":"2019-09-05"},{"c":"33231585000100","r":"ALL SERVICES-G. CEDRO ASSESSORIA LTDA","n":"ALL SERVICES-G. CEDRO ASSESSORIA","m":"ANAPOLIS","d":"2019-04-03"},{"c":"33325184002910","r":"ALSCO BRASIL LTDA","n":null,"m":"GOIANIA","d":"1998-12-10"},{"c":"31861950000134","r":"ALVEX GESTAO E HIGIENIZACAO TEXTIL LTDA","n":"LAVANDERIA ALVEX","m":"GOIANIA","d":"2018-10-25"},{"c":"36312446000107","r":"AROMA DO VALE EMPREENDIMENTOS LTDA","n":"AROMA DO VALE","m":"NIQUELANDIA","d":"2020-02-10"},{"c":"00886257005828","r":"ATMOSFERA GESTAO E HIGIENIZACAO DE TEXTEIS S.A.","n":null,"m":"ANAPOLIS","d":"2024-04-12"},{"c":"00886257006042","r":"ATMOSFERA GESTAO E HIGIENIZACAO DE TEXTEIS S.A.","n":null,"m":"GOIANIA","d":"2024-08-01"},{"c":"00886257006395","r":"ATMOSFERA GESTAO E HIGIENIZACAO DE TEXTEIS S.A.","n":null,"m":"INHUMAS","d":"2025-06-12"},{"c":"29736089001102","r":"ATMOSFERA GESTAO E HIGIENIZACAO DE UNIFORMES LTDA","n":null,"m":"INHUMAS","d":"2024-12-17"},{"c":"29736089000807","r":"ATMOSFERA GESTAO E HIGIENIZACAO DE UNIFORMES LTDA","n":null,"m":"RIO VERDE","d":"2009-01-16"},{"c":"19286679000155","r":"AUDAZ SERVICOS E COMERCIO LTDA","n":"AUDAZ","m":"SENADOR CANEDO","d":"2013-11-05"},{"c":"55486976000108","r":"AUTHENTIC TRADE & INDUSTRY LTDA","n":"AUTHENTIC TRADE & INDUSTRY","m":"ITAPIRAPUA","d":"2024-06-11"},{"c":"13597279000184","r":"B R LAUNDRY INDUSTRIA, COMERCIO E SERVICOS LTDA","n":"ELIS","m":"ANAPOLIS","d":"2011-04-27"},{"c":"13597279000265","r":"B R LAUNDRY INDUSTRIA, COMERCIO E SERVICOS LTDA","n":"BR LAUNDRY","m":"GOIANIA","d":"2018-04-02"},{"c":"03499743000146","r":"BARBARAKA COSMETICOS LTDA","n":"BARBARAKA","m":"RIO VERDE","d":"1999-11-01"},{"c":"15103114000134","r":"BENFICA REZENDE SERVICOS LTDA","n":"LAVBEM LAVANDERIA","m":"SAO LUIS DE MONTES BELOS","d":"2012-02-23"},{"c":"20429482000107","r":"BICHARADA DOG HOTEL LTDA","n":"BICHARADA DOG HOTEL","m":"SENADOR CANEDO","d":"2014-06-10"},{"c":"65334167000134","r":"BORGES ALUGUEL LTDA","n":"BORGES ALUGUEL","m":"CALDAS NOVAS","d":"2026-02-25"},{"c":"14739847000105","r":"BR AUTOMATION ECOLOGICAL SYSTEM IN LAUNDRY LTDA","n":"BR SISTEMA & SERVICOS ESPECIAIS","m":"APARECIDA DE GOIANIA","d":"2011-12-08"},{"c":"21564545000281","r":"BRASILAV GESTAO E HIGIENIZACAO TEXTIL LTDA","n":"BRASILLAV LAVANDERIA HOSPITALAR","m":"GOIANIA","d":"2020-09-17"},{"c":"47414524000192","r":"BRASILIA SERVICOS EXPRESSOS LTDA","n":"BRASILIA SERVICOS DE LIMPEZA","m":"VALPARAISO DE GOIAS","d":"2022-08-04"},{"c":"47414524000273","r":"BRASILIA SERVICOS EXPRESSOS LTDA","n":"BRASILIA SERVICOS DE LIMPEZA","m":"VALPARAISO DE GOIAS","d":"2025-10-28"},{"c":"23397168000188","r":"CA AGROSERV LTDA","n":null,"m":"JATAI","d":"2015-10-01"},{"c":"37819055000138","r":"CALDAS LAUNDRY LTDA","n":"CALDAS LAUNDRY","m":"CALDAS NOVAS","d":"2020-07-22"},{"c":"05872995000102","r":"CENTERLAV LAVANDERIA INDUSTRIAL LTDA","n":"CENTERLAV LAVANDERIA","m":"APARECIDA DE GOIANIA","d":"2003-08-19"},{"c":"26548893000106","r":"CHALES RECANTO PARAISO LTDA","n":"CHALES RECANTO PARAISO","m":"ALTO PARAISO DE GOIAS","d":"2016-11-16"},{"c":"66242417000179","r":"CIDADE & MENEZES LAVANDERIA LTDA","n":"JATAI EXPRESS","m":"JATAI","d":"2026-04-14"},{"c":"28038269000186","r":"CILMAR PERISSINOTTO LTDA","n":"MIX CLEAN LAVANDERIA","m":"MINEIROS","d":"2017-06-26"},{"c":"65491481000120","r":"CL LAVANDERIA LTDA","n":"CL LAVANDERIA","m":"CALDAS NOVAS","d":"2026-03-04"},{"c":"26439708000137","r":"CLAUDIA DENIANE DE MORAES PEDROSO","n":"TOALHAO","m":"ANAPOLIS","d":"2016-10-27"},{"c":"62055460000174","r":"CLEAN PRO BRASIL SOLUCOES INTELIGENTES EM HIGIENIZACAO LTDA","n":"CLEAN PRO BRASIL","m":"ITUMBIARA","d":"2025-08-04"},{"c":"28143164000197","r":"CLEIDE RONALDO DOMINGOS NETO","n":"CSW PRESTADOR DE SERVICOS","m":"NIQUELANDIA","d":"2017-07-10"},{"c":"27623265000100","r":"CLUBE ITAPEMA LTDA","n":"CLUBE ITAPEMA","m":"POSSE","d":"2017-04-28"},{"c":"44223902000162","r":"CONCEITO EM LAVANDERIA INDUSTRIAL LTDA","n":"CONCEITO LAVANDERIA","m":"CALDAS NOVAS","d":"2021-11-12"},{"c":"59200585000136","r":"CONCEITO LAVANDERIA CN LTDA","n":"CONCEITO LAVANDERIA","m":"CALDAS NOVAS","d":"2025-01-30"},{"c":"21022245000190","r":"CONCEITO LAVANDERIA PRODUTOS DE LIMPEZA E DESCARTAVEIS LTDA","n":"CONCEITO LAVANDERIA","m":"CALDAS NOVAS","d":"2014-09-11"},{"c":"08757925000193","r":"CONFECCAO E ALFAIATARIA GOIANA LTDA","n":"NEW DRY LAVANDERIA","m":"GOIANIA","d":"2007-04-11"},{"c":"13788248000100","r":"CONFORT LAVANDERIA LTDA","n":"CONFORT LAVANDERIA","m":"CALDAS NOVAS","d":"2011-06-06"},{"c":"11137492000188","r":"COSTA SANTOS IMPORTACOES E EXPORTACOES LTDA","n":"ACQUA BRONZE","m":"CERES","d":"2009-09-10"},{"c":"11137492000269","r":"COSTA SANTOS IMPORTACOES E EXPORTACOES LTDA","n":"ACQUA BRONZE","m":"CERES","d":"2017-10-04"},{"c":"26815846000173","r":"CSB HOTELARIA COMERCIO E SERVICOS LTDA","n":"IMPERIO HOTEL","m":"CACU","d":"2017-01-06"},{"c":"59207033000150","r":"CVSANTOS - SERVICOS E GESTAO LTDA","n":"CVSANTOS SERVICOS","m":"PIRANHAS","d":"2025-01-31"},{"c":"44154911000149","r":"DANYELLA BRAGA DE QUEIROZ LAVANDERIA QUEIROZ","n":"LAVANDERIA QUEIROZ","m":"HIDROLANDIA","d":"2021-11-08"},{"c":"38381041000148","r":"DAVINIS LAVANDERIA E SERVICOS LTDA","n":"DAVINIS LAVANDERIA","m":"GOIANIA","d":"2020-09-09"},{"c":"59056414000185","r":"DC GERADORES LTDA","n":"DC GERADORES","m":"ANAPOLIS","d":"2025-01-23"},{"c":"40114236000173","r":"DENIM WASH LAVANDERIA ESPECIALIZADA LTDA","n":"DENIM WASH LAVANDERIA ESPECIALIZADA","m":"GOIANIA","d":"2020-12-15"},{"c":"11454202000120","r":"DINAMICA AMBIENTAL E INCORPORADORA LTDA","n":"DINAMICA AMBIENTAL E INCORPORADORA","m":"SANTA HELENA DE GOIAS","d":"2009-12-15"},{"c":"62232778000183","r":"DJ LAVANDERIA LTDA","n":"DJ LAVANDERIA INDUSTRIAL","m":"GOIANIA","d":"2025-08-14"},{"c":"53966324000145","r":"DOIS TEMPOS LTDA","n":null,"m":"GOIANIA","d":"2024-02-19"},{"c":"17479671000180","r":"DUELAV LAVANDERIAS LTDA","n":"DUELAV LAVANDERIAS","m":"ANAPOLIS","d":"2013-01-17"},{"c":"04629190000161","r":"DULCENI FIDELIS MARQUES DA SILVA","n":null,"m":"CATALAO","d":"2001-08-21"},{"c":"15543042000146","r":"E CANDIDA DE OLIVEIRA","n":"LAVEBEM","m":"GOIANIA","d":"2012-04-27"},{"c":"19367750000124","r":"E-3M BEBIDAS E CONVENIENCIAS LTDA","n":"E-3M BEBIDAS E CONVENIENCIAS","m":"GOIANIA","d":"2013-11-28"},{"c":"43468397000153","r":"ECO WASH LTDA","n":"LAVO CATALAO","m":"CATALAO","d":"2021-09-10"},{"c":"60052963000160","r":"ECOCLEAN DISTRIBUIDORA E SERVICOS LTDA","n":"ECOCLEAN SOLUCOES","m":"ITUMBIARA","d":"2025-03-24"},{"c":"60052963000241","r":"ECOCLEAN DISTRIBUIDORA E SERVICOS LTDA","n":"ECOCLEAN SOLUCOES","m":"ITUMBIARA","d":"2026-04-30"},{"c":"34156954000100","r":"EDSON FELIPE FERREIRA VARGAS 02118012160","n":null,"m":"GOIANAPOLIS","d":"2019-07-09"},{"c":"61830835000163","r":"ELENICE DA COSTA PINTO - ETERNA MAGIA LAVANDERIA","n":"ETERNA MAGIA LAVANDERIA","m":"GOIAS","d":"2025-07-21"},{"c":"43976236000170","r":"ELIABIA CASSIMIRO SILVA  LTDA","n":"LAVO","m":"GOIANESIA","d":"2021-10-22"},{"c":"14173022000168","r":"ENEIDE DA SILVA RAMOS 04471343610","n":"LAVANDERIA E PASSADORIA ALVORADA","m":"ITUMBIARA","d":"2011-08-24"},{"c":"28170688000177","r":"EVOLIMP COMERCIO E SERVICOS LTDA","n":"EVOLIMP COMERCIO E SERVICOS","m":"ITUMBIARA","d":"2017-07-12"},{"c":"41521376000129","r":"FIGUEREDO E SANTOS LIMPEZA E CUIDADOS LTDA","n":"CONSTANCIA LIMP. HIGIENIZACAO & CUIDADOS EM FACILITIES","m":"GOIANIA","d":"2021-04-09"},{"c":"27933840000163","r":"FMC EMPREENDIMENTOS LTDA","n":"ALVA INDUSTRIA COMERCIO E SERVICOS","m":"ANAPOLIS","d":"2017-06-09"},{"c":"03479405000223","r":"FUNCIONAL LAVANDERIA LTDA","n":null,"m":"ALTO HORIZONTE","d":"2022-05-16"},{"c":"10218716000113","r":"G J DE SOUSA JUNIOR LTDA","n":"NEWTOPBET SONIC HALL DANCE","m":"PARANAIGUARA","d":"2008-07-28"},{"c":"18687351000188","r":"GAO ASSISTENCIA LTDA","n":"GAO ASSISTENCIA","m":"APARECIDA DE GOIANIA","d":"2013-08-08"},{"c":"36245583000168","r":"GAO SERVICOS DE LOCACAO E LAVANDERIA LTDA","n":"GAO LAVANDERIA","m":"APARECIDA DE GOIANIA","d":"2020-02-04"},{"c":"48361721000153","r":"GARMENT  LAVANDERIA INDUSTRIAL LTDA","n":null,"m":"GOIANIA","d":"2022-10-20"},{"c":"45142803000119","r":"GIRLENE O. SANTOS LTDA","n":"WG GESTAO DE ACOMODACOES E HIGIENE","m":"CALDAS NOVAS","d":"2022-02-03"},{"c":"22335379000123","r":"GLOBAL SERVICE LAVANDERIA LTDA","n":"GTX SERVICE","m":"GOIANIA","d":"2015-04-27"},{"c":"42110519000172","r":"GOLD GIRLS FACCAO E CONFECCAO DE ROUPAS LTDA","n":"GOLD GIRLS FACCAO E CONFECCAO DE ROUPAS","m":"GOIANIA","d":"2021-05-27"},{"c":"56022447000116","r":"GOLDEN LAVANDERIA LTDA","n":null,"m":"GOIANIA","d":"2024-07-22"},{"c":"03007197000189","r":"GYN - LOCACAO DE MAQUINAS E UTILIDADES LTDA","n":"CHEM-DRY GYN","m":"GOIANIA","d":"1999-01-04"},{"c":"58665731000136","r":"HB EMPREENDIMENTOS E SERVICOS LTDA","n":"HB EMPREENDIMENTOS","m":"ITUMBIARA","d":"2025-01-07"},{"c":"25143788000116","r":"HIGIMAXI PRESTACAO E TERCERIZACAO DE SERVICOS LTDA","n":"HIGIMAXI","m":"ITUMBIARA","d":"2016-07-06"},{"c":"07713772000110","r":"HIGIPAPER DISTRIBUIDORA E COMERCIO LTDA","n":"HIGIPAPER SOLUCOES EM HIGIENE, LIMPEZA E DESCARTAVEIS","m":"ITUMBIARA","d":"2005-12-01"},{"c":"18405020000108","r":"HL LAVANDERIA LTDA.","n":null,"m":"JATAI","d":"2013-07-02"},{"c":"57737903000177","r":"HOME DECOR LTDA","n":"HOME DECOR","m":"QUIRINOPOLIS","d":"2024-10-17"},{"c":"37628070000107","r":"HOSPITAL LUCIANO CHAVES LTDA","n":"NSTITUTO SAO VICENTE DE PAULO - HOSPITAL LUCIANO CHAVES","m":"FORMOSA","d":"1993-02-02"},{"c":"01552868000167","r":"HOSPITAL SANTA LUCIA LTDA","n":"HOSPITAL VITTA","m":"GOIANIA","d":"1966-09-29"},{"c":"01552868000248","r":"HOSPITAL SANTA LUCIA LTDA","n":"HOSPITAL VITTA","m":"GOIANIA","d":"2014-06-24"},{"c":"61041328000140","r":"HOTEL NOSSO CANTINHO LTDA","n":"HOTEL NOSSO CANTINHO","m":"COLINAS DO SUL","d":"2025-05-28"},{"c":"05457250000179","r":"IACOM COMERCIO E PRESTACAO DE SERVICOS LTDA","n":"IACOM SABOR & CIA","m":"SENADOR CANEDO","d":"2003-01-09"},{"c":"40456101000196","r":"IMPAX SOLUTIONS SOLUCOES E TECNOLOGIA LTDA","n":"IMPAX SOLUTIONS","m":"GOIANIA","d":"2021-01-19"},{"c":"18599173000133","r":"INFINITI COMERCIO E SERVICOS LTDA","n":"INFINITI COMERCIO E SERVICOS","m":"GOIANIA","d":"2013-07-31"},{"c":"49260046000139","r":"INOVA PRIME GESTAO DE NEGOCIOS LTDA","n":"INOVA PRIME GESTAO DE NEGOCIOS","m":"CALDAS NOVAS","d":"2023-01-19"},{"c":"27390816000125","r":"INOVAR - NUCLEO DE ASSISTENCIA, CAPACITACAO E SERVICOS LTDA","n":"INOVAR","m":"BRAZABRANTES","d":"2017-03-27"},{"c":"25201306000137","r":"INSTITUTO NACIONAL DE EDUCACAO, PESQUISA, INSTRUCAO, CONCURSOS PUBLICOS E SEGURANCA PUBLICA - INEP BRASIL","n":"INEP BRASIL","m":"GOIANIA","d":"2015-11-09"},{"c":"00983626000165","r":"ISABELA CRISTINA LAVANDERIA E TINTURARIA LTDA","n":"LAVANDERIA JOHN CLER","m":"GOIANIA","d":"1996-01-02"},{"c":"31081275000120","r":"ISABELA CRISTINA LIMA COSTA","n":null,"m":"DOVERLANDIA","d":"2018-08-01"},{"c":"54453809000106","r":"JARDIM LAVANDERIA EXPRESS LTDA","n":"JARDIM LAVANDERIA","m":"GOIANIA","d":"2024-03-25"},{"c":"13075458000151","r":"JB BARBOSA FILHO LAVANDEIRA LTDA","n":"LAVANDERIA JOHN CLER","m":"GOIANIA","d":"2011-01-04"},{"c":"42915117000307","r":"JM SERVICOS DE VESTUARIO LTDA","n":null,"m":"GOIANIA","d":"2022-11-28"},{"c":"42915117000145","r":"JM SERVICOS DE VESTUARIO LTDA","n":null,"m":"GOIANIA","d":"2021-07-29"},{"c":"61674785000172","r":"JUSTUS PARTICIPACOES LTDA","n":"LICITA JUSTUS","m":"ABADIANIA","d":"2025-07-10"},{"c":"51815743000150","r":"KELLY ROBERTA AZEVEDO SILVA GRACIANO LTDA","n":null,"m":"MOZARLANDIA","d":"2023-08-15"},{"c":"30924317000185","r":"L E EMPREENDIMENTOS LTDA","n":"GOLD","m":"GOIANIA","d":"2018-07-13"},{"c":"55201072000199","r":"LAV EXPRESS LAVANDERIA RV LTDA","n":"LAV EXPRESS LAVANDERIA","m":"RIO VERDE","d":"2024-05-20"},{"c":"22307784000138","r":"LAV SEC LAVANDERIA LTDA","n":"LAV SEC LAVANDERIA","m":"CATALAO","d":"2015-04-23"},{"c":"20102774000130","r":"LAVANDERIA AGUA LIMPA LTDA","n":"LAVANDERIA AGUA LIMPA","m":"SAO SIMAO","d":"2014-04-17"},{"c":"67939640000132","r":"LAVANDERIA AGUAS LINDAS LTDA","n":"LAVANDERIA AGUAS LINDAS","m":"AGUAS LINDAS DE GOIAS","d":"2026-07-09"},{"c":"01003110000170","r":"LAVANDERIA CISLAV LTDA","n":"CISLAV LAVANDERIAS","m":"GOIANIA","d":"1984-10-22"},{"c":"01003110000927","r":"LAVANDERIA CISLAV LTDA","n":"CISLAV LAVANDERIAS","m":"GOIANIA","d":"2017-01-16"},{"c":"43159149000120","r":"LAVANDERIA ESPECIALIZADA EM CORTINAS E TAPETES LIMPO LTDA","n":"LIMPO LAVANDERIA","m":"ANAPOLIS","d":"2021-08-17"},{"c":"64500984000152","r":"LAVANDERIA LUZ E VIDA LTDA","n":"LAVANDERIA LUZ E VIDA","m":"GOIANIA","d":"2026-01-15"},{"c":"37618154000151","r":"LAVANDERIA MORAIS LTDA","n":"ULTRA LIMPO","m":"ANAPOLIS","d":"1993-01-22"},{"c":"36265671000121","r":"LAVANDERIA MUNDIAL LTDA","n":"LAVANDERIA MUNDIAL","m":"GOIANIA","d":"2020-02-05"},{"c":"11665987000180","r":"LAVANDERIA NEROPOLIS LTDA","n":null,"m":"NEROPOLIS","d":"2010-03-09"},{"c":"45041285000147","r":"LAVANDERIA PRISMA LTDA","n":"LAVANDERIA PRISMA","m":"GOIANIA","d":"2022-01-27"},{"c":"52375682000110","r":"LAVANDERIA SHALOM LTDA","n":null,"m":"GOIANIA","d":"2023-09-30"},{"c":"08807690000105","r":"LAVANDERIA SOL NASCENTE LTDA","n":"LAVANDERIA SOL NASCENTE","m":"NIQUELANDIA","d":"2007-05-04"},{"c":"23235667000179","r":"LAVANDERIA VITORIA LTDA","n":"LAVANDERIA VITORIA","m":"PIRENOPOLIS","d":"2015-09-09"},{"c":"06272575001898","r":"LAVEBRAS GESTAO DE TEXTEIS S.A.","n":"LAVE BRAS","m":"PALMEIRAS DE GOIAS","d":"2009-02-17"},{"c":"06272575003327","r":"LAVEBRAS GESTAO DE TEXTEIS S.A.","n":"********","m":"PALMEIRAS DE GOIAS","d":"2010-11-18"},{"c":"06272575010455","r":"LAVEBRAS GESTAO DE TEXTEIS S.A.","n":null,"m":"SANTA FE DE GOIAS","d":"2020-08-05"},{"c":"06272575010374","r":"LAVEBRAS GESTAO DE TEXTEIS S.A.","n":null,"m":"BURITI ALEGRE","d":"2020-08-04"},{"c":"26068396000100","r":"LAVEST LAVANDERIA E ESTERILIZACAO LTDA","n":"LAVEST","m":"ANAPOLIS","d":"2016-08-30"},{"c":"65703165000175","r":"LAVEY LAVANDERIA EXPRESS LTDA","n":"LAVEY LAVANDERIA","m":"GOIANIA","d":"2026-03-16"},{"c":"55187228000124","r":"LAVO ACMD LTDA","n":"LAVO SAO MIGUEL DO ARAGUAIA GOIAS","m":"SAO MIGUEL DO ARAGUAIA","d":"2024-05-20"},{"c":"65472901000121","r":"LAVO ERA PTC LTDA","n":"LAVO LOZANDES","m":"GOIANIA","d":"2026-02-27"},{"c":"55304882000170","r":"LAVO JB LTDA","n":"LAVO GOIANIA SETOR UNIAO","m":"GOIANIA","d":"2024-05-28"},{"c":"62804066000191","r":"LAVO LAVANDERIA APFS LTDA","n":"LAVO GOIANIA AEROPORTO","m":"GOIANIA","d":"2025-09-19"},{"c":"50276840000150","r":"LAVO LAVANDERIA GOIANIA CIDADE JARDIM LTDA","n":"LAVO GOIANIA CIDADE JARDIM","m":"GOIANIA","d":"2023-04-11"},{"c":"50276992000152","r":"LAVO LAVANDERIA GOIANIA PERIMETRAL NORTE LTDA","n":"LAVO GOIANIA PERIMETRAL NORTE","m":"GOIANIA","d":"2023-04-11"},{"c":"50012561000189","r":"LAVO LAVANDERIA MTFB LTDA","n":"LAVO LAVANDERIA GOIANIA UNIVERSITARIO.","m":"GOIANIA","d":"2023-03-21"},{"c":"54338768000107","r":"LAVO MATOS & SILVA LTDA","n":"LAVO LUZIANIA VILA JURACY","m":"LUZIANIA","d":"2024-03-15"},{"c":"47119118000105","r":"LAVO SALGADO FILHO JATAI GOIAS LTDA","n":"LAVO SALGADO FILHO JATAI GOIAS","m":"JATAI","d":"2022-07-12"},{"c":"49580192000141","r":"LAVO SAO SIMAO RESIDENCIAL CEMIG LTDA","n":"LAVO SAO SIMAO RESIDENCIAL CEMIG","m":"SAO SIMAO","d":"2023-02-13"},{"c":"59309665000124","r":"LAVO VPJB JARDIM DAS ESMERALDAS LTDA","n":"LAVO JARDIM DAS ESMERALDAS","m":"APARECIDA DE GOIANIA","d":"2025-02-05"},{"c":"63128414000110","r":"LEV LAV SAM LTDA","n":"LEV LAV LAVANDERIA EXPRESS","m":"NOVA CRIXAS","d":"2025-10-10"},{"c":"00482840001371","r":"LIDERANCA LIMPEZA E CONSERVACAO LTDA","n":"LIDERANCA SERVICOS","m":"GOIANIA","d":"2018-08-24"},{"c":"65526775000140","r":"LIGLIMP HIGIENIZACAO E APLICACAO DE PELICULAS LTDA","n":"LIGLIMPGO","m":"GOIANIA","d":"2026-03-05"},{"c":"21711733000104","r":"LIMPIA - LOCACAO DE TEXTEIS E COMERCIO DE PRODUTOS DE HIGIENE LTDA","n":"LIMPIA LAVANDERIA","m":"GOIANIA","d":"2015-01-20"},{"c":"48630643000145","r":"LU TECNOLOGIA SERVICOS E MEIOS DE PAGAMENTO LTDA","n":null,"m":"PALMEIRAS DE GOIAS","d":"2022-11-16"},{"c":"35101216000128","r":"LUCIA MACIEL","n":"RAIO DE SOL LAVANDERIA","m":"CALDAS NOVAS","d":"2019-10-07"},{"c":"12641982000180","r":"LUCY CLEYDE BARRETO DA SILVA","n":"LUCY BARRETO MODA CASA","m":"GOIANIA","d":"2010-10-05"},{"c":"24970939000147","r":"LUMINOSITA UNIFORMES E SERVICOS LTDA","n":"LUMINOSITA","m":"GOIANIA","d":"2016-06-09"},{"c":"12208881000110","r":"LUZIA DE CARVALHO BIZERRA","n":null,"m":"LUZIANIA","d":"2010-07-12"},{"c":"30461944000127","r":"MACHADO LAVANDERIA LTDA","n":"CLEANGSIA LAVANDERIA","m":"GOIANESIA","d":"2018-05-15"},{"c":"22572599000170","r":"MACIEL & SERVICOS LTDA","n":"APOIO LAVANDERIA","m":"CALDAS NOVAS","d":"2015-06-02"},{"c":"59088135000284","r":"MAGIA DE LAVAR LTDA","n":"MAGIA DE LAVAR","m":"CRISTALINA","d":"2026-05-12"},{"c":"59088135000101","r":"MAGIA DE LAVAR LTDA","n":"MAGIA DE LAVAR","m":"CRISTALINA","d":"2025-01-24"},{"c":"58541354000123","r":"MAJU LAVANDERIAS EXPRESS LTDA","n":"MARIA EXPRESS GOIANIA LESTE VILA NOVA","m":"GOIANIA","d":"2024-12-23"},{"c":"07598755000189","r":"MARCILENE PAULINA DE OLIVEIRA SIQUEIRA","n":"LAVANDERIA MASTER","m":"ANAPOLIS","d":"2005-09-09"},{"c":"34153004000121","r":"MARIA DO SOCORRO DE AGUIAR","n":"LAVANDERIA VALPARAISO","m":"VALPARAISO DE GOIAS","d":"2019-07-09"},{"c":"28056163000105","r":"MASTER COMERCIO E SERVICOS LTDA","n":"MASTER","m":"GOIANIA","d":"2017-06-28"},{"c":"28131438000128","r":"MASTERSERV GESTAO DE FACILITES LTDA.","n":"MASTERSERV GESTAO DE FACILITES","m":"GOIANIA","d":"2017-07-07"},{"c":"24620109000190","r":"MEDY HIGIENIZACAO PROFISSIONAL LTDA","n":"MEDY","m":"JATAI","d":"2016-04-18"},{"c":"33242802000248","r":"MEIBORG LAVANDERIAS LTDA","n":null,"m":"APARECIDA DE GOIANIA","d":"2019-05-15"},{"c":"49580878000132","r":"MG LAVANDERIAS LAVO LTDA","n":null,"m":"GOIANIA","d":"2023-02-13"},{"c":"26592951000190","r":"MK COMERCIO E PRESTACAO DE SERVICOS LTDA","n":"PORTUGA FRIOS E EMBALAGENS","m":"SENADOR CANEDO","d":"2016-11-23"},{"c":"23028518000139","r":"MOMENTOS PRODUCOES FOTOGRAFICAS LTDA","n":"MOMENTOS","m":"GOIANIA","d":"2015-08-07"},{"c":"35759605000226","r":"MUNDO DAS FARMACIAS LTDA","n":"MUNDO DAS FARMACIAS","m":"APARECIDA DE GOIANIA","d":"2025-11-27"},{"c":"47223091000198","r":"MUNDO DAS PLANTAS FLORICULTURA LTDA","n":"MUNDO DAS PLANTAS FLORICULTURA","m":"CHAPADAO DO CEU","d":"2022-07-20"},{"c":"11850150000100","r":"N B SOARES LTDA","n":"LAVANDERIA S-10","m":"CAMPINORTE","d":"2010-04-20"},{"c":"21313901000103","r":"NEROPOLIS LAVANDERIA LTDA","n":"LAVANDERIA NEROPOLIS","m":"NEROPOLIS","d":"2014-10-29"},{"c":"41675845000164","r":"NILDA BATISTA 26515810890","n":null,"m":"INHUMAS","d":"2021-04-23"},{"c":"20477335000102","r":"NOVAERA LIMPEZA URBANA E SERVICOS LTDA","n":"NOVAERA","m":"GOIANIA","d":"2014-06-18"},{"c":"11737128000159","r":"OLF MODAS E VESTUARIO LTDA","n":"OLF","m":"GOIANIA","d":"2010-03-24"},{"c":"20865979000178","r":"PAIXAO TRANSPORTE E TURISMO LTDA","n":"PAIXAO TRANSPORTE E TURISMO","m":"PILAR DE GOIAS","d":"2014-08-19"},{"c":"29630877000148","r":"PATRICK ADVISORY LTDA","n":"VANGUARDX","m":"GOIANIA","d":"2018-02-06"},{"c":"31161806000195","r":"PAULA BEATRIZ DE MOURA FARIA 04278669100","n":null,"m":"GOIANIA","d":"2018-08-09"},{"c":"54969363000169","r":"POLO INDUSTRIA BRASILEIRA DE UNIFORMES LTDA","n":null,"m":"GOIANIA","d":"2024-05-02"},{"c":"59470798000188","r":"PRATIC SUPRIMENTOS E LAVANDERIA LTDA","n":"PRATIC SUPRIMENTOS E LAVANDERIA","m":"CALDAS NOVAS","d":"2025-02-14"},{"c":"18534798000117","r":"PRIMAX DISTRIBUIDORA LTDA","n":"PRIMAX","m":"ANAPOLIS","d":"2013-07-22"},{"c":"65483678000118","r":"PRO LAV EXPRESS LTDA","n":null,"m":"BELA VISTA DE GOIAS","d":"2026-03-03"},{"c":"66866665000190","r":"PROCLEAN LAVANDERIA PROFISSIONAL LTDA","n":"PROCLEAN LAVANDERIA PROFISSIONAL","m":"HIDROLANDIA","d":"2026-05-18"},{"c":"65795672000186","r":"PROMOSTORE POLO GROUP CONFECCOES LTDA","n":null,"m":"GOIANIA","d":"2026-03-19"},{"c":"26919791000141","r":"R M SOLUCAO EM PRODUTOS DE LIMPEZA E LAVANDERIA LTDA","n":"SOLUCAO PRODUTOS DE LIMPEZA","m":"APARECIDA DE GOIANIA","d":"2017-01-20"},{"c":"49356340000149","r":"RBS SOLUTIONS X RBS SOLUCOES EMPRESARIAIS LTDA","n":"RBS SOLUTIONS X RBS SOLUCOES EMPRESARIAIS","m":"APARECIDA DE GOIANIA","d":"2023-01-26"},{"c":"18114016000190","r":"REAL DIGITAL SERVICOS E SOLUCOES EM TECNOLOGIA LTDA","n":"REAL DIGITAL","m":"GOIANIA","d":"2013-05-14"},{"c":"36770431000184","r":"REAL LAV LTDA","n":"REAL SERVICOS","m":"CERES","d":"2020-03-26"},{"c":"14090600000100","r":"REI DAS MAQUINAS MANUTENCAO E EQUIPAMENTOS LTDA","n":"REI DAS MAQUINAS","m":"ITUMBIARA","d":"2011-08-09"},{"c":"29856331000100","r":"REN GESTAO E PRESTACAO DE SERVICOS LTDA","n":"R&N GESTAO E PRESTACAO DE SERVICOS","m":"GOIANIA","d":"2018-03-06"},{"c":"13979063000183","r":"RIO VERDE LAVANDERIA HOSPITALAR LTDA","n":"RIO VERDE LAVANDERIA HOSPITALAR","m":"RIO VERDE","d":"2011-07-06"},{"c":"31034501000112","r":"RM CLEAN PRODUTOS DE LIMPEZA E LAVANDERIA LTDA","n":"RM CLEAN","m":"GOIANIA","d":"2018-07-26"},{"c":"10567714000130","r":"RP LAVANDERIA LTDA.","n":"LAVIP LAVANDERIA","m":"RIO VERDE","d":"2009-01-08"},{"c":"35117591000166","r":"S C MEDEIROS","n":"MEDEIROS PRESTADORA DE SERVICOS","m":"RIO VERDE","d":"2019-10-08"},{"c":"33227684000118","r":"S O LIMA LTDA","n":"PANGARE LANCHES","m":"ALTO HORIZONTE","d":"2019-04-02"},{"c":"06163883000137","r":"S T P DUARTE POUSADA REFLEXO E TRANQUILIDADE","n":"POUSADINHA REFLEXO E TRANQUILIDADE","m":"CRISTALINA","d":"2004-03-23"},{"c":"03566923000101","r":"S. NOLLI COMERCIO E SERVICOS LTDA","n":"J.NOLLI COMERCIO E SERVICOS","m":"GOIANIA","d":"1999-12-08"},{"c":"65644438000158","r":"SAN SEBASTIAN RESTAURANTE LTDA","n":"SAN SEBASTIAN RESTAURANTE","m":"BARRO ALTO","d":"2026-03-11"},{"c":"48032179000195","r":"SEBASTIANA PASSOS FERREIRA RESTAURANTE","n":"SAN SEBASTIAN RESTAURANTE","m":"BARRO ALTO","d":"2022-09-21"},{"c":"50540852000140","r":"SELD LAVANDERIA EXPRESS LTDA","n":"SELD LAVANDERIA EXPRESS","m":"ALTO HORIZONTE","d":"2023-05-04"},{"c":"20546182000612","r":"SERVBRASIL SOLUCOES EM LAVANDERIA LTDA","n":"SERVBRASIL","m":"JARAGUA","d":"2021-06-21"},{"c":"20546182000701","r":"SERVBRASIL SOLUCOES EM LAVANDERIA LTDA","n":"SERVBRASIL","m":"URUACU","d":"2021-06-21"},{"c":"20546182001503","r":"SERVBRASIL SOLUCOES EM LAVANDERIA LTDA","n":null,"m":"FORMOSA","d":"2022-10-28"},{"c":"20546182001260","r":"SERVBRASIL SOLUCOES EM LAVANDERIA LTDA","n":null,"m":"AGUAS LINDAS DE GOIAS","d":"2022-05-16"},{"c":"20546182001775","r":"SERVBRASIL SOLUCOES EM LAVANDERIA LTDA","n":"SERVBRASIL SOLUCOES EM ALIMENTACAO, LIMPEZA E LAVANDERI","m":"TRINDADE","d":"2023-02-02"},{"c":"47094421000192","r":"SETEFARMA INDUSTRIA, COMERCIO, IMPORTACAO E EXPORTACAO DE PRODUTOS PARA SAUDE LTDA","n":"SETEFARMA DISTRIBUIDORA","m":"APARECIDA DE GOIANIA","d":"2022-07-11"},{"c":"38285172000121","r":"SETEHOSPITALAR DISTRIBUIDORA, IMPORTADORA E EXPORTADORA DE MOVEIS E EQUIPAMENTOS HOSPITALAR LTDA","n":"SETEHOSPITALAR DISTRIBUIDORA","m":"APARECIDA DE GOIANIA","d":"2020-08-31"},{"c":"62243239000140","r":"SN ADMINISTRACAO LTDA","n":"ADM THERMAS DO ARACA","m":"CALDAS NOVAS","d":"2025-08-15"},{"c":"21434195000239","r":"SS COMERCIO E PRESTACAO DE SERVICOS LTDA","n":null,"m":"SENADOR CANEDO","d":"2023-01-25"},{"c":"21434195000158","r":"SS COMERCIO E PRESTACAO DE SERVICOS LTDA","n":"QUALIMAIS","m":"SENADOR CANEDO","d":"2014-11-18"},{"c":"45705492000159","r":"STM ENGENHARIA LTDA","n":null,"m":"ANAPOLIS","d":"2022-03-18"},{"c":"59741985000159","r":"SW LAVANDERIA E SERVICOS LTDA","n":"SW LAVANDERIA","m":"TRINDADE","d":"2025-03-05"},{"c":"23171670000176","r":"TATIANA SUSSUARANA BATISTA CORDEIRO 81210647168","n":null,"m":"GOIANIA","d":"2015-08-28"},{"c":"04635547000114","r":"TEXTIL MED DISTRIBUIDORA DE PRODUTOS E SERVICOS HOSPITALARES LTDA","n":"TEXTIL MED","m":"ANAPOLIS","d":"2001-08-30"},{"c":"04635547000203","r":"TEXTIL MED DISTRIBUIDORA DE PRODUTOS E SERVICOS HOSPITALARES LTDA","n":"TEXTIL MED","m":"ANAPOLIS","d":"2017-07-27"},{"c":"00289462000170","r":"TOALHEIRO ANHANGUERA SERVICOS DE LAVANDERIA LTDA","n":"TOALEX","m":"GOIANIA","d":"1983-10-17"},{"c":"51461353000120","r":"TOK LAVANDERIA EXPRESSO LTDA","n":"TOK LAVANDERIA EXPRESSO","m":"AGUAS LINDAS DE GOIAS","d":"2023-07-18"},{"c":"58179858000145","r":"TOKESTERIL SOLUCOES EM LAVANDERIA LTDA","n":"TOKESTERIL SOLUCOES EM LAVANDERIA","m":"GOIANIA","d":"2024-11-21"},{"c":"18097166000133","r":"TOP CLEAN LAVANDERIA HOSPITALAR LTDA","n":"TOP CLEAN LAVANDERIA","m":"APARECIDA DE GOIANIA","d":"2013-05-11"},{"c":"31603659000166","r":"TOP LIMP LAVANDERIA LTDA","n":"TOP LIMP LAVANDERIA","m":"GOIANIA","d":"2018-09-25"},{"c":"25695402000189","r":"UNILIMP SERVICOS LTDA","n":"UNILIMP","m":"VALPARAISO DE GOIAS","d":"2016-08-15"},{"c":"33008821000123","r":"UNITERCEIRIZACAO DE MAO DE OBRA LTDA","n":"UNILAVA","m":"GOIANAPOLIS","d":"2019-03-13"},{"c":"52315597000167","r":"URBAN WASH LTDA","n":null,"m":"FORMOSA","d":"2023-09-26"},{"c":"10331475000114","r":"VHB COMERCIO E SERVICOS LTDA","n":"VHB COMERCIO E SERVICOS","m":"GOIANIA","d":"2008-09-11"},{"c":"58642697000184","r":"VITTA CAMINHO PRIME LTDA","n":null,"m":"GOIANIA","d":"2025-01-06"},{"c":"60016054000177","r":"VITTA SERVICOS EM SAUDE LTDA","n":"VITTA SERVICOS EM SAUDE","m":"RIO VERDE","d":"2025-03-21"},{"c":"29674018000150","r":"VIVA COR LAVANDERIA LTDA","n":"LAVANDERIA VIVA COR","m":"HIDROLANDIA","d":"2018-02-13"},{"c":"62104577000109","r":"VIVA SERVICOS ESPECIALIZADOS LTDA","n":"VIVA SERVICOS ESPECIALIZADOS","m":"GOIANIRA","d":"2025-08-06"},{"c":"37794082000101","r":"WS PARTINER LLC LTDA","n":"WS PARTINER LLC","m":"VARJAO","d":"2020-07-21"},{"c":"35626581000156","r":"YMR - ENGENHARIA, SERVICOS E EMPREENDIMENTOS LTDA","n":"YMR ENGENHARIA E SERVICOS","m":"PIRANHAS","d":"2019-11-26"}]